{
    "Jalen Green": {
        "MIN": 31.327213039418233,
        "FGM": 6.038344893330871,
        "FGA": 14.39478171250161,
        "FG3M": 2.237282887462909,
        "FG3A": 6.4917591617853585,
        "REB": 4.970509218677242,
        "AST": 3.2233414256650166,
        "STL": 0.6964022732327083,
        "BLK": 0.35394778979555996,
        "PF": 1.1185176664881824,
        "PTS": 19.254309790891927,
        "FTA": 3.969261150336128,
        "FTM": 3.3570357407663147,
        "FG_PCT": 0.3790545685064634,
        "FG3_PCT": 0.3019400508120278,
        "FT_PCT": 0.6935022333274452,
        "ptsConfFloor": 16.279898094670173,
        "ptsConfMid": 20.513131313131314,
        "ptsConfTop": 24.74636453159245,
        "astConfFloor": 2.706442533464846,
        "astConfMid": 3.4939393939393937,
        "astConfTop": 4.281436254413942,
        "rebConfFloor": 3.649608901417563,
        "rebConfMid": 4.949494949494949,
        "rebConfTop": 6.249380997572337,
        "team": "HOU",
        "fanduel_pts": 22.5,
        "fanduel_reb": 5.5,
        "fanduel_ast": 3.5,
        "fanduel_threes": 2.5,
        "fanduel_blk": 0,
        "fanduel_stl": 0.5,
        "pick_pts": "UNDER",
        "pick_reb": "UNDER",
        "pick_ast": "UNDER",
        "pick_3s": "UNDER",
        "pick_blk": "OVER",
        "pick_stl": "OVER"
    },
    "Amen Thompson": "N/A",
    "Dillon Brooks": {
        "MIN": 31.8681219248018,
        "FGM": 4.931618427807938,
        "FGA": 10.906715997210867,
        "FG3M": 2.0302956107325687,
        "FG3A": 4.950640956429252,
        "REB": 3.4947907600761,
        "AST": 1.723122612487194,
        "STL": 0.7563980091762309,
        "BLK": 0.0850819716977931,
        "PF": 3.3100128381673026,
        "PTS": 13.78182707302017,
        "FTA": 2.692414836938671,
        "FTM": 2.2658342502331212,
        "FG_PCT": 0.45940153521472643,
        "FG3_PCT": 0.4190152310889885,
        "FT_PCT": 0.6099824636015673,
        "ptsConfFloor": 8.94464472574245,
        "ptsConfMid": 11.2046783625731,
        "ptsConfTop": 13.464711999403752,
        "astConfFloor": 1.2576156901756212,
        "astConfMid": 1.8280701754385964,
        "astConfTop": 2.3985246607015713,
        "rebConfFloor": 2.4057547585876433,
        "rebConfMid": 3.3976608187134496,
        "rebConfTop": 4.389566878839257,
        "team": "HOU",
        "fanduel_pts": 12.5,
        "fanduel_reb": 3.5,
        "fanduel_ast": 0,
        "fanduel_threes": 1.5,
        "fanduel_blk": 0,
        "fanduel_stl": 0.5,
        "pick_pts": "OVER",
        "pick_reb": "UNDER",
        "pick_ast": "OVER",
        "pick_3s": "OVER",
        "pick_blk": "OVER",
        "pick_stl": "OVER"
    },
    "Jabari Smith": "N/A",
    "Dalano Banton": {
        "MIN": 11.850399994872447,
        "FGM": 2.6252648208895177,
        "FGA": 4.229092590350172,
        "FG3M": 0.3113281805162292,
        "FG3A": 1.4230715459685062,
        "REB": 3.4876249092854903,
        "AST": 2.049846611175045,
        "STL": 0.3194424362573559,
        "BLK": 0.18255743521993983,
        "PF": 0.8972770881421945,
        "PTS": 6.0994856980117085,
        "FTA": 0.8791015820985381,
        "FTM": 1.1139106446396294,
        "FG_PCT": 0.33678688322459743,
        "FG3_PCT": 0.07247801678965189,
        "FT_PCT": 0.3369240435999231,
        "ptsConfFloor": 8.800908172805855,
        "ptsConfMid": 12.822222222222221,
        "ptsConfTop": 16.843536271638587,
        "astConfFloor": 1.7922699355839786,
        "astConfMid": 2.4957264957264957,
        "astConfTop": 3.1991830558690126,
        "rebConfFloor": 2.5773198008406166,
        "rebConfMid": 3.8376068376068377,
        "rebConfTop": 5.0978938743730575,
        "team": "POR",
        "fanduel_pts": 14.5,
        "fanduel_reb": 4.5,
        "fanduel_ast": 3.5,
        "fanduel_threes": 0,
        "fanduel_blk": 0,
        "fanduel_stl": 0,
        "pick_pts": "UNDER",
        "pick_reb": "UNDER",
        "pick_ast": "UNDER",
        "pick_3s": "OVER",
        "pick_blk": "OVER",
        "pick_stl": "OVER"
    },
    "Donovan Mitchell": {
        "MIN": 36.25550955614016,
        "FGM": 10.689635871948168,
        "FGA": 20.607946416161813,
        "FG3M": 3.43857401608265,
        "FG3A": 8.745732382208493,
        "REB": 5.4876396437856485,
        "AST": 6.727818224262421,
        "STL": 1.8919192531058506,
        "BLK": 0.601520948090952,
        "PF": 2.1491875490756347,
        "PTS": 28.404044220916752,
        "FTA": 5.989352366963017,
        "FTM": 5.123131245936976,
        "FG_PCT": 0.44770637497679433,
        "FG3_PCT": 0.3555644045043691,
        "FT_PCT": 0.858814107801323,
        "ptsConfFloor": 21.98339724027558,
        "ptsConfMid": 25.85138888888889,
        "ptsConfTop": 29.7193805375022,
        "astConfFloor": 4.999412447726315,
        "astConfMid": 5.826388888888889,
        "astConfTop": 6.6533653300514635,
        "rebConfFloor": 4.514312710373809,
        "rebConfMid": 5.280555555555556,
        "rebConfTop": 6.046798400737302,
        "team": "CLE",
        "fanduel_pts": 24.5,
        "fanduel_reb": 4.5,
        "fanduel_ast": 5.5,
        "fanduel_threes": 3.5,
        "fanduel_blk": 0,
        "fanduel_stl": 1.5,
        "pick_pts": "OVER",
        "pick_reb": "OVER",
        "pick_ast": "OVER",
        "pick_3s": "UNDER",
        "pick_blk": "OVER",
        "pick_stl": "OVER"
    },
    "Isaac Okoro": {
        "MIN": 25.520929166214323,
        "FGM": 3.9373463857456823,
        "FGA": 6.548199743047961,
        "FG3M": 0.8647971470192388,
        "FG3A": 2.8126666231367525,
        "REB": 3.226454503027778,
        "AST": 1.9362894785421647,
        "STL": 0.8829502048397069,
        "BLK": 0.5055104359887034,
        "PF": 2.232039732246144,
        "PTS": 9.527478727785194,
        "FTA": 2.2314352611290134,
        "FTM": 1.5132159778988896,
        "FG_PCT": 0.44069381157562454,
        "FG3_PCT": 0.34543001557544584,
        "FT_PCT": 0.38951759826518345,
        "ptsConfFloor": 9.279041792171718,
        "ptsConfMid": 11.106432748538012,
        "ptsConfTop": 12.933823704904304,
        "astConfFloor": 1.672968268692144,
        "astConfMid": 2.1391812865497077,
        "astConfTop": 2.6053943044072714,
        "rebConfFloor": 2.7239779298455438,
        "rebConfMid": 3.6748538011695904,
        "rebConfTop": 4.625729672493637,
        "team": "CLE",
        "fanduel_pts": 10.5,
        "fanduel_reb": 3.5,
        "fanduel_ast": 0,
        "fanduel_threes": 1.5,
        "fanduel_blk": 0,
        "fanduel_stl": 0,
        "pick_pts": "UNDER",
        "pick_reb": "UNDER",
        "pick_ast": "OVER",
        "pick_3s": "UNDER",
        "pick_blk": "OVER",
        "pick_stl": "OVER"
    },
    "Dean Wade": {
        "MIN": 21.33264229200224,
        "FGM": 1.412541580905464,
        "FGA": 4.590609319404574,
        "FG3M": 1.582974706803837,
        "FG3A": 4.351665039178793,
        "REB": 3.699861914118239,
        "AST": 0.759475039437748,
        "STL": 0.974648953328906,
        "BLK": 0.21924622309984443,
        "PF": 1.6345866976745653,
        "PTS": -1,
        "FTA": 0.7355945285203284,
        "FTM": 0.5272973539005704,
        "FG_PCT": 0.4215948932320224,
        "FG3_PCT": 0.3183808664198522,
        "FT_PCT": 0.24030139643151768,
        "ptsConfFloor": 2.1511214647521317,
        "ptsConfMid": 5.818518518518519,
        "ptsConfTop": 9.485915572284904,
        "astConfFloor": 0.3840351179984592,
        "astConfMid": 0.8209876543209876,
        "astConfTop": 1.2579401906435161,
        "rebConfFloor": 2.7502355120878357,
        "rebConfMid": 3.745679012345679,
        "rebConfTop": 4.741122512603522
    },
    "Jarrett Allen": {
        "MIN": 32.13296522372908,
        "FGM": 6.575392204952866,
        "FGA": 9.876676432107564,
        "FG3M": -0.00886323164994163,
        "FG3A": 0.02161047678727454,
        "REB": 11.988812849867678,
        "AST": 2.26043601978908,
        "STL": 0.7280065105281877,
        "BLK": 0.9942297345780748,
        "PF": 2.104291999593586,
        "PTS": 14.687254459239716,
        "FTA": 4.176124665569182,
        "FTM": 3.162335572404528,
        "FG_PCT": 0.6493546228810932,
        "FG3_PCT": -0.00884217315219387,
        "FT_PCT": 0.5988130007845501,
        "ptsConfFloor": 14.856309191792528,
        "ptsConfMid": 18.015664845173042,
        "ptsConfTop": 21.175020498553554,
        "astConfFloor": 1.9831853805848383,
        "astConfMid": 2.54608378870674,
        "astConfTop": 3.10898219682864,
        "rebConfFloor": 9.55918988575,
        "rebConfMid": 11.612750455373407,
        "rebConfTop": 13.666311024996814,
        "team": "CLE",
        "fanduel_pts": 16.5,
        "fanduel_reb": 12.5,
        "fanduel_ast": 0,
        "fanduel_threes": 0,
        "fanduel_blk": 1.5,
        "fanduel_stl": 0,
        "pick_pts": "UNDER",
        "pick_reb": "UNDER",
        "pick_ast": "OVER",
        "pick_3s": "UNDER",
        "pick_blk": "UNDER",
        "pick_stl": "OVER"
    },
    "Fred VanVleet": {
        "MIN": 36.56231429833956,
        "FGM": 5.100406112550184,
        "FGA": 13.026712579589985,
        "FG3M": 2.9335402124000445,
        "FG3A": 7.591353437938481,
        "REB": 3.6229262435015706,
        "AST": 7.419895313733669,
        "STL": 0.9748641174369109,
        "BLK": 0.8314710177852785,
        "PF": 2.166086389116583,
        "PTS": 17.90255761597686,
        "FTA": 3.186842871099169,
        "FTM": 2.5103571718088813,
        "FG_PCT": 0.4101456031478794,
        "FG3_PCT": 0.3767350159168751,
        "FT_PCT": 0.7059517906692799,
        "ptsConfFloor": 15.81228561256355,
        "ptsConfMid": 18.310734463276834,
        "ptsConfTop": 20.809183313990122,
        "astConfFloor": 6.867026427211023,
        "astConfMid": 7.76120527306968,
        "astConfTop": 8.655384118928337,
        "rebConfFloor": 2.7967990922987336,
        "rebConfMid": 3.72090395480226,
        "rebConfTop": 4.645008817305786,
        "team": "HOU",
        "fanduel_pts": 19.5,
        "fanduel_reb": 3.5,
        "fanduel_ast": 7.5,
        "fanduel_threes": 2.5,
        "fanduel_blk": 0,
        "fanduel_stl": 1.5,
        "pick_pts": "UNDER",
        "pick_reb": "OVER",
        "pick_ast": "UNDER",
        "pick_3s": "OVER",
        "pick_blk": "OVER",
        "pick_stl": "UNDER"
    },
    "Andrew Nembhard": {
        "MIN": 22.227789057910137,
        "FGM": 3.606898871256487,
        "FGA": 6.468334160965339,
        "FG3M": 0.7857109127390134,
        "FG3A": 1.877961992953575,
        "REB": 2.5666663058880475,
        "AST": 3.7427518380436164,
        "STL": 0.999179382977424,
        "BLK": 0.11947806788856632,
        "PF": 2.4706167268477937,
        "PTS": 8.313040643509753,
        "FTA": 0.43282419223136626,
        "FTM": 0.6110702032361437,
        "FG_PCT": 0.5044214994553364,
        "FG3_PCT": 0.3510368368229667,
        "FT_PCT": 0.15027955271169496,
        "ptsConfFloor": 6.523458137173875,
        "ptsConfMid": 8.695178197064989,
        "ptsConfTop": 10.866898256956105,
        "astConfFloor": 2.8311684200316307,
        "astConfMid": 3.646960167714885,
        "astConfTop": 4.4627519153981385,
        "rebConfFloor": 2.0493209282550247,
        "rebConfMid": 2.79664570230608,
        "rebConfTop": 3.543970476357135,
        "team": "IND",
        "fanduel_pts": 8.5,
        "fanduel_reb": 0,
        "fanduel_ast": 3.5,
        "fanduel_threes": 0,
        "fanduel_blk": 0,
        "fanduel_stl": 0,
        "pick_pts": "UNDER",
        "pick_reb": "OVER",
        "pick_ast": "OVER",
        "pick_3s": "OVER",
        "pick_blk": "OVER",
        "pick_stl": "OVER"
    },
    "Aaron Nesmith": {
        "MIN": 26.45086665774925,
        "FGM": 4.820365868143348,
        "FGA": 7.895245190563664,
        "FG3M": 2.0215425251858643,
        "FG3A": 4.599576310580851,
        "REB": 3.9100151072894036,
        "AST": 1.2803580259533855,
        "STL": 1.112719806258533,
        "BLK": 0.8348550438374394,
        "PF": 3.396727559867429,
        "PTS": 9.924812310429209,
        "FTA": 1.6167485368451424,
        "FTM": 0.9916252278199038,
        "FG_PCT": 0.48195565448926936,
        "FG3_PCT": 0.4825127951676831,
        "FT_PCT": 0.48083308560006843,
        "ptsConfFloor": 9.726491620723946,
        "ptsConfMid": 11.998084291187737,
        "ptsConfTop": 14.269676961651532,
        "astConfFloor": 1.029517329934999,
        "astConfMid": 1.3659003831417624,
        "astConfTop": 1.7022834363485257,
        "rebConfFloor": 2.8383609020039393,
        "rebConfMid": 3.6421455938697314,
        "rebConfTop": 4.445930285735525,
        "team": "IND",
        "fanduel_pts": 14.5,
        "fanduel_reb": 4.5,
        "fanduel_ast": 0,
        "fanduel_threes": 2.5,
        "fanduel_blk": 0,
        "fanduel_stl": 0,
        "pick_pts": "UNDER",
        "pick_reb": "UNDER",
        "pick_ast": "OVER",
        "pick_3s": "UNDER",
        "pick_blk": "OVER",
        "pick_stl": "OVER"
    },
    "Pascal Siakam": {
        "MIN": 34.24005780902015,
        "FGM": 7.350855652544225,
        "FGA": 15.615158762772936,
        "FG3M": 0.958397217681368,
        "FG3A": 3.320227694093225,
        "REB": 6.912019821615305,
        "AST": 3.826894515292037,
        "STL": 0.7491656888670041,
        "BLK": 0.2651489695735841,
        "PF": 2.340968860028031,
        "PTS": 21.19588709260336,
        "FTA": 5.049193010805029,
        "FTM": 3.9170506985622233,
        "FG_PCT": 0.5299547600217267,
        "FG3_PCT": 0.33834667166497084,
        "FT_PCT": 0.725842795605089,
        "ptsConfFloor": 17.525369494514823,
        "ptsConfMid": 19.59316239316239,
        "ptsConfTop": 21.66095529180996,
        "astConfFloor": 3.139057920016183,
        "astConfMid": 3.911111111111111,
        "astConfTop": 4.68316430220604,
        "rebConfFloor": 6.146093987694975,
        "rebConfMid": 7.625641025641027,
        "rebConfTop": 9.105188063587077,
        "team": "IND",
        "fanduel_pts": 20.5,
        "fanduel_reb": 7.5,
        "fanduel_ast": 3.5,
        "fanduel_threes": 0,
        "fanduel_blk": 0,
        "fanduel_stl": 0,
        "pick_pts": "OVER",
        "pick_reb": "UNDER",
        "pick_ast": "OVER",
        "pick_3s": "OVER",
        "pick_blk": "OVER",
        "pick_stl": "OVER"
    },
    "Myles Turner": {
        "MIN": 27.842072755852946,
        "FGM": 6.229674666616103,
        "FGA": 11.928585847894382,
        "FG3M": 1.3764750158000023,
        "FG3A": 4.003451860231443,
        "REB": 7.265096979079743,
        "AST": 1.5687573077567107,
        "STL": 0.5149482589933404,
        "BLK": 1.7667391725373214,
        "PF": 3.164340613583683,
        "PTS": 16.676164522744983,
        "FTA": 4.535390680565762,
        "FTM": 3.172163960896355,
        "FG_PCT": 0.4938543307101963,
        "FG3_PCT": 0.3371827118841947,
        "FT_PCT": 0.7604958255933113,
        "ptsConfFloor": 15.322559056775688,
        "ptsConfMid": 18.33862433862434,
        "ptsConfTop": 21.354689620472993,
        "astConfFloor": 0.7444366040113946,
        "astConfMid": 1.3841269841269843,
        "astConfTop": 2.0238173642425736,
        "rebConfFloor": 5.560623452345939,
        "rebConfMid": 6.655026455026455,
        "rebConfTop": 7.749429457706971,
        "team": "IND",
        "fanduel_pts": 16.5,
        "fanduel_reb": 7.5,
        "fanduel_ast": 0,
        "fanduel_threes": 1.5,
        "fanduel_blk": 1.5,
        "fanduel_stl": 0,
        "pick_pts": "OVER",
        "pick_reb": "UNDER",
        "pick_ast": "OVER",
        "pick_3s": "UNDER",
        "pick_blk": "OVER",
        "pick_stl": "OVER"
    },
    "Vasilije Micic": "N/A",
    "Cam Thomas": {
        "MIN": 31.68146846624738,
        "FGM": 8.520593244064385,
        "FGA": 18.605915466782363,
        "FG3M": 2.2766044643724364,
        "FG3A": 5.920500905765284,
        "REB": 4.059110093880694,
        "AST": 3.6325019443068602,
        "STL": 0.8152316208575254,
        "BLK": 0.31180329532419077,
        "PF": 2.5120074393467844,
        "PTS": 24.92864619175585,
        "FTA": 4.74804494965428,
        "FTM": 4.135418190139339,
        "FG_PCT": 0.4327623508522851,
        "FG3_PCT": 0.3315986935149051,
        "FT_PCT": 0.759225258705438,
        "ptsConfFloor": 18.26328909295097,
        "ptsConfMid": 21.92941176470588,
        "ptsConfTop": 25.59553443646079,
        "astConfFloor": 2.504559867607691,
        "astConfMid": 3.286274509803922,
        "astConfTop": 4.067989152000152,
        "rebConfFloor": 2.7695684534587226,
        "rebConfMid": 4.02875816993464,
        "rebConfTop": 5.287947886410557,
        "team": "BKN",
        "fanduel_pts": 23.5,
        "fanduel_reb": 3.5,
        "fanduel_ast": 3.5,
        "fanduel_threes": 2.5,
        "fanduel_blk": 0,
        "fanduel_stl": 0,
        "pick_pts": "OVER",
        "pick_reb": "OVER",
        "pick_ast": "OVER",
        "pick_3s": "UNDER",
        "pick_blk": "OVER",
        "pick_stl": "OVER"
    },
    "Mikal Bridges": {
        "MIN": 34.96019811355218,
        "FGM": 6.593888869605959,
        "FGA": 16.496477166821993,
        "FG3M": 2.2387149776002153,
        "FG3A": 6.0634825055413994,
        "REB": 4.127187417014626,
        "AST": 3.64193663378232,
        "STL": 1.0702492624706745,
        "BLK": 0.4364383005954138,
        "PF": 1.706465218575276,
        "PTS": 20.9673163252979,
        "FTA": 3.7060797739350213,
        "FTM": 3.108992319569667,
        "FG_PCT": 0.46671785001742044,
        "FG3_PCT": 0.37475618384415454,
        "FT_PCT": 0.6742394958063832,
        "ptsConfFloor": 15.840419725961093,
        "ptsConfMid": 18.62121212121212,
        "ptsConfTop": 21.40200451646315,
        "astConfFloor": 2.9345240607538177,
        "astConfMid": 3.8818181818181814,
        "astConfTop": 4.829112302882546,
        "rebConfFloor": 3.2184577304201922,
        "rebConfMid": 4.153535353535354,
        "rebConfTop": 5.0886129766505155,
        "team": "BKN",
        "fanduel_pts": 19.5,
        "fanduel_reb": 4.5,
        "fanduel_ast": 3.5,
        "fanduel_threes": 2.5,
        "fanduel_blk": 0,
        "fanduel_stl": 1.5,
        "pick_pts": "OVER",
        "pick_reb": "UNDER",
        "pick_ast": "OVER",
        "pick_3s": "UNDER",
        "pick_blk": "OVER",
        "pick_stl": "UNDER"
    },
    "Dorian Finney-Smith": {
        "MIN": 29.146774427606942,
        "FGM": 2.7543163830171213,
        "FGA": 7.978804278746258,
        "FG3M": 2.2499740371285695,
        "FG3A": 5.659412706791747,
        "REB": 4.342077429640286,
        "AST": 1.6315909459320406,
        "STL": 0.9065495670450303,
        "BLK": 0.5082133894618636,
        "PF": 2.322895774862067,
        "PTS": 9.230083809294191,
        "FTA": 0.5494495231246138,
        "FTM": 0.3669045019587073,
        "FG_PCT": 0.41847055985881293,
        "FG3_PCT": 0.37671576749615693,
        "FT_PCT": 0.10827668785540503,
        "ptsConfFloor": 7.20695285179088,
        "ptsConfMid": 9.609356725146199,
        "ptsConfTop": 12.01176059850152,
        "astConfFloor": 1.1853649969644875,
        "astConfMid": 1.887719298245614,
        "astConfTop": 2.590073599526741,
        "rebConfFloor": 3.516899408084495,
        "rebConfMid": 4.539181286549708,
        "rebConfTop": 5.56146316501492,
        "team": "BKN",
        "fanduel_pts": 7.5,
        "fanduel_reb": 4.5,
        "fanduel_ast": 0,
        "fanduel_threes": 1.5,
        "fanduel_blk": 0,
        "fanduel_stl": 0,
        "pick_pts": "OVER",
        "pick_reb": "UNDER",
        "pick_ast": "OVER",
        "pick_3s": "OVER",
        "pick_blk": "OVER",
        "pick_stl": "OVER"
    },
    "Nic Claxton": {
        "MIN": 28.791156557530304,
        "FGM": 5.360105784730226,
        "FGA": 8.676120113393763,
        "FG3M": 0.0,
        "FG3A": 0.11097703125061738,
        "REB": 9.561522741334555,
        "AST": 2.5571607205004794,
        "STL": 0.48551859387324875,
        "BLK": 2.428259132877023,
        "PF": 2.35395189832884,
        "PTS": 11.087561112358681,
        "FTA": 2.154538982149443,
        "FTM": 1.2804234857772232,
        "FG_PCT": 0.6579221815679741,
        "FG3_PCT": 0.032489207934293086,
        "FT_PCT": 0.38511215588851655,
        "ptsConfFloor": 11.303084010047064,
        "ptsConfMid": 12.96031746031746,
        "ptsConfTop": 14.617550910587857,
        "astConfFloor": 1.9941715533549953,
        "astConfMid": 2.6075396825396826,
        "astConfTop": 3.22090781172437,
        "rebConfFloor": 7.885708747150019,
        "rebConfMid": 9.027777777777779,
        "rebConfTop": 10.169846808405536,
        "team": "BKN",
        "fanduel_pts": 12.5,
        "fanduel_reb": 9.5,
        "fanduel_ast": 0,
        "fanduel_threes": 0,
        "fanduel_blk": 1.5,
        "fanduel_stl": 0,
        "pick_pts": "UNDER",
        "pick_reb": "OVER",
        "pick_ast": "OVER",
        "pick_3s": "UNDER",
        "pick_blk": "OVER",
        "pick_stl": "OVER"
    },
    "Jacob Gilyard": {
        "MIN": 13.92751756562896,
        "FGM": 1.1400876800283846,
        "FGA": 2.247867803837953,
        "FG3M": 1.1010085574572126,
        "FG3A": 1.8902629708599847,
        "REB": 1.1829347646236261,
        "AST": 3.096433367422628,
        "STL": 0.5494229804315105,
        "BLK": 0.10921008437573154,
        "PF": 0.8023975935592325,
        "PTS": 2.8885712568865483,
        "FTA": -0.030070097180181624,
        "FTM": 0.04052943186751271,
        "FG_PCT": 0.2835962102092323,
        "FG3_PCT": 0.3776350226883612,
        "FT_PCT": 0.058339483801319696,
        "ptsConfFloor": 3.795933825815968,
        "ptsConfMid": 6.203003003003002,
        "ptsConfTop": 8.61007218019004,
        "astConfFloor": 3.2950814596961684,
        "astConfMid": 3.9801801801801795,
        "astConfTop": 4.665278900664191,
        "rebConfFloor": 0.8533367215536508,
        "rebConfMid": 1.4318318318318317,
        "rebConfTop": 2.0103269421100127
    },
    "Tyrese Maxey": {
        "MIN": 39.48736095172845,
        "FGM": 9.766024463409032,
        "FGA": 21.807415554207772,
        "FG3M": 2.8520526564178494,
        "FG3A": 8.695662648522095,
        "REB": 3.7167100182345245,
        "AST": 5.131496870243867,
        "STL": 1.0184431831453862,
        "BLK": 0.7175198217690428,
        "PF": 2.1892512433692968,
        "PTS": 31.657149384595012,
        "FTA": 6.356678219755516,
        "FTM": 5.142434460978984,
        "FG_PCT": 0.4421214675530148,
        "FG3_PCT": 0.3762165188293827,
        "FT_PCT": 0.8260462327223793,
        "ptsConfFloor": 23.06262908679253,
        "ptsConfMid": 26.598830409356726,
        "ptsConfTop": 30.135031731920918,
        "astConfFloor": 4.532245636738201,
        "astConfMid": 5.175438596491229,
        "astConfTop": 5.818631556244256,
        "rebConfFloor": 2.8412596984555196,
        "rebConfMid": 3.728654970760234,
        "rebConfTop": 4.616050243064948,
        "team": "PHI",
        "fanduel_pts": 27.5,
        "fanduel_reb": 4.5,
        "fanduel_ast": 5.5,
        "fanduel_threes": 3.5,
        "fanduel_blk": 0,
        "fanduel_stl": 0.5,
        "pick_pts": "OVER",
        "pick_reb": "UNDER",
        "pick_ast": "UNDER",
        "pick_3s": "UNDER",
        "pick_blk": "OVER",
        "pick_stl": "OVER"
    },
    "Kelly Oubre Jr.": {
        "MIN": 27.12845811012558,
        "FGM": 5.303514211191269,
        "FGA": 9.662748553184588,
        "FG3M": 1.0111923967146368,
        "FG3A": 3.973464569554276,
        "REB": 5.528495637231965,
        "AST": 1.481595324679693,
        "STL": 1.182846389915042,
        "BLK": 0.43075726943747367,
        "PF": 2.6574245987869336,
        "PTS": 12.499549804498894,
        "FTA": 2.6752078402683264,
        "FTM": 1.5831032230455637,
        "FG_PCT": 0.4485230442721569,
        "FG3_PCT": 0.2668562158682871,
        "FT_PCT": 0.48718747005931085,
        "ptsConfFloor": 13.612076322442071,
        "ptsConfMid": 16.649056603773584,
        "ptsConfTop": 19.686036885105096,
        "astConfFloor": 0.9095846203152176,
        "astConfMid": 1.4754716981132077,
        "astConfTop": 2.0413587759111973,
        "rebConfFloor": 4.346529299458308,
        "rebConfMid": 5.537526205450734,
        "rebConfTop": 6.728523111443159
    },
    "Mo Bamba": {
        "MIN": 10.853651935197,
        "FGM": 1.5290532527636074,
        "FGA": 2.888473724515087,
        "FG3M": 0.2014798219306766,
        "FG3A": 0.7598335228062464,
        "REB": 3.56979126370294,
        "AST": 0.8663553022686081,
        "STL": 0.31489603551628365,
        "BLK": 0.7854484736396785,
        "PF": 1.218833345537929,
        "PTS": -1,
        "FTA": 0.7245099767212785,
        "FTM": 0.5499008013471394,
        "FG_PCT": 0.4319387389962272,
        "FG3_PCT": 0.15835642053594762,
        "FT_PCT": 0.15764436313797525,
        "ptsConfFloor": 2.304644140219693,
        "ptsConfMid": 3.5550505050505046,
        "ptsConfTop": 4.805456869881318,
        "astConfFloor": 0.29053840098659683,
        "astConfMid": 0.8570707070707071,
        "astConfTop": 1.4236030131548174,
        "rebConfFloor": 2.5933976531970946,
        "rebConfMid": 3.65,
        "rebConfTop": 4.706602346802906
    },
    "Jordan Poole": {
        "MIN": 28.836061904918783,
        "FGM": 6.348882136750767,
        "FGA": 14.659593323280536,
        "FG3M": 2.1047070901894918,
        "FG3A": 6.90566034024876,
        "REB": 3.2693247824722396,
        "AST": 4.792799649145756,
        "STL": 1.2724070868862511,
        "BLK": 0.32326072207189455,
        "PF": 3.1127898296140764,
        "PTS": 16.613229650879063,
        "FTA": 2.425770700643098,
        "FTM": 2.2351960858070568,
        "FG_PCT": 0.4061485352397021,
        "FG3_PCT": 0.22393891476514277,
        "FT_PCT": 0.6083553981122972,
        "ptsConfFloor": 13.074715882772246,
        "ptsConfMid": 17.182291666666668,
        "ptsConfTop": 21.28986745056109,
        "astConfFloor": 3.4116946487492696,
        "astConfMid": 4.287847222222222,
        "astConfTop": 5.163999795695174,
        "rebConfFloor": 2.4333006681858262,
        "rebConfMid": 3.1430555555555557,
        "rebConfTop": 3.852810442925285
    },
    "Tre Mann": {
        "MIN": 20.98608879199028,
        "FGM": 3.1635605485132454,
        "FGA": 8.137622503492624,
        "FG3M": 1.0556524264468667,
        "FG3A": 3.789298304239167,
        "REB": 4.481147254995365,
        "AST": 4.545864699179104,
        "STL": 0.8401724538581532,
        "BLK": 0.04096694971244136,
        "PF": 1.0752877435722699,
        "PTS": 9.272869886011827,
        "FTA": 1.0840043776794472,
        "FTM": 0.5145128344716848,
        "FG_PCT": 0.3060135299012699,
        "FG3_PCT": 0.25213763226452784,
        "FT_PCT": 0.2524771903430337,
        "ptsConfFloor": 7.359687475943535,
        "ptsConfMid": 9.795726495726496,
        "ptsConfTop": 12.231765515509453,
        "astConfFloor": 2.571591922871486,
        "astConfMid": 3.835042735042735,
        "astConfTop": 5.098493547213985,
        "rebConfFloor": 3.370763338499982,
        "rebConfMid": 4.242735042735043,
        "rebConfTop": 5.1147067469701035,
        "team": "CHA",
        "fanduel_pts": 11.5,
        "fanduel_reb": 4.5,
        "fanduel_ast": 4.5,
        "fanduel_threes": 0,
        "fanduel_blk": 0,
        "fanduel_stl": 0,
        "pick_pts": "UNDER",
        "pick_reb": "UNDER",
        "pick_ast": "OVER",
        "pick_3s": "OVER",
        "pick_blk": "OVER",
        "pick_stl": "OVER"
    },
    "Brandon Miller": "N/A",
    "Miles Bridges": "N/A",
    "Nick Richards": {
        "MIN": 25.764239894748876,
        "FGM": 4.350108612066946,
        "FGA": 5.9150048095132455,
        "FG3M": -0.017760656828008606,
        "FG3A": -0.020981514397294426,
        "REB": 9.258162638399865,
        "AST": 0.8242142569298344,
        "STL": 0.38763999636498253,
        "BLK": 1.2848579365168296,
        "PF": 2.6821412629523183,
        "PTS": 9.024370064574178,
        "FTA": 2.6542372971769397,
        "FTM": 1.8847651739642102,
        "FG_PCT": 0.7035395810279695,
        "FG3_PCT": -0.021304775427126277,
        "FT_PCT": 0.5491583525625395,
        "ptsConfFloor": 7.514087238688888,
        "ptsConfMid": 9.796491228070176,
        "ptsConfTop": 12.07889521745146,
        "astConfFloor": 0.28113562273440323,
        "astConfMid": 0.6912280701754385,
        "astConfTop": 1.1013205176164738,
        "rebConfFloor": 7.8814588378091885,
        "rebConfMid": 9.57076023391813,
        "rebConfTop": 11.260061630027069,
        "team": "CHA",
        "fanduel_pts": 10.5,
        "fanduel_reb": 8.5,
        "fanduel_ast": 0,
        "fanduel_threes": 0,
        "fanduel_blk": 1.5,
        "fanduel_stl": 0,
        "pick_pts": "UNDER",
        "pick_reb": "OVER",
        "pick_ast": "OVER",
        "pick_3s": "UNDER",
        "pick_blk": "UNDER",
        "pick_stl": "OVER"
    },
    "Kyle Lowry": {
        "MIN": 30.27607753754896,
        "FGM": 2.3303185475416295,
        "FGA": 6.945534360579853,
        "FG3M": 1.7760529357543438,
        "FG3A": 5.263196142374104,
        "REB": 3.359655774853958,
        "AST": 3.8742896514264205,
        "STL": 1.1765387607181557,
        "BLK": 0.41543660044055686,
        "PF": 2.6087191281501525,
        "PTS": 8.252917210005078,
        "FTA": 1.9881832321137611,
        "FTM": 1.159705340761327,
        "FG_PCT": 0.32822508889269914,
        "FG3_PCT": 0.3152068816944511,
        "FT_PCT": 0.48680683514230183,
        "ptsConfFloor": 5.221601931541589,
        "ptsConfMid": 7.5749408983451545,
        "ptsConfTop": 9.928279865148719,
        "astConfFloor": 3.117167774210172,
        "astConfMid": 4.308274231678488,
        "astConfTop": 5.499380689146801,
        "rebConfFloor": 2.405589123798405,
        "rebConfMid": 2.8316784869976357,
        "rebConfTop": 3.257767850196867,
        "team": "PHI",
        "fanduel_pts": 8.5,
        "fanduel_reb": 3.5,
        "fanduel_ast": 4.5,
        "fanduel_threes": 1.5,
        "fanduel_blk": 0,
        "fanduel_stl": 0,
        "pick_pts": "UNDER",
        "pick_reb": "UNDER",
        "pick_ast": "UNDER",
        "pick_3s": "OVER",
        "pick_blk": "OVER",
        "pick_stl": "OVER"
    },
    "Brandon Ingram": {
        "MIN": 33.13931112820491,
        "FGM": 8.953412822884305,
        "FGA": 16.67402558463635,
        "FG3M": 1.611950438641349,
        "FG3A": 4.060987374513958,
        "REB": 4.936080555658312,
        "AST": 5.719851429114482,
        "STL": 0.747135460128483,
        "BLK": 0.6415368036829164,
        "PF": 2.123685992042878,
        "PTS": 21.924648371539593,
        "FTA": 3.7858337802763806,
        "FTM": 2.891254051918497,
        "FG_PCT": 0.490742765301607,
        "FG3_PCT": 0.3584328168211493,
        "FT_PCT": 0.7966397705166511,
        "ptsConfFloor": 15.5514533586471,
        "ptsConfMid": 18.51111111111111,
        "ptsConfTop": 21.470768863575127,
        "astConfFloor": 5.453606569480727,
        "astConfMid": 6.355555555555555,
        "astConfTop": 7.257504541630383,
        "rebConfFloor": 4.440733117021395,
        "rebConfMid": 5.266666666666667,
        "rebConfTop": 6.092600216311939,
        "team": "NOP",
        "fanduel_pts": 0,
        "fanduel_reb": 0,
        "fanduel_ast": 0,
        "fanduel_threes": 0,
        "fanduel_blk": 0,
        "fanduel_stl": 0,
        "pick_pts": "OVER",
        "pick_reb": "OVER",
        "pick_ast": "OVER",
        "pick_3s": "OVER",
        "pick_blk": "OVER",
        "pick_stl": "OVER"
    },
    "Herbert Jones": {
        "MIN": 28.581437343773583,
        "FGM": 4.442921348538438,
        "FGA": 8.192621054833795,
        "FG3M": 1.3876642460924384,
        "FG3A": 3.5954361520470637,
        "REB": 3.5650361430782365,
        "AST": 2.4582812893962114,
        "STL": 1.1319344541644396,
        "BLK": 1.1700857961255775,
        "PF": 3.0601769796194924,
        "PTS": 10.284419268654963,
        "FTA": 1.723019514472816,
        "FTM": 1.67303878424414,
        "FG_PCT": 0.4708922477626451,
        "FG3_PCT": 0.3873247453149522,
        "FT_PCT": 0.6685016495971079,
        "ptsConfFloor": 7.581927489767739,
        "ptsConfMid": 10.083060109289617,
        "ptsConfTop": 12.584192728811496,
        "astConfFloor": 2.1751597645908283,
        "astConfMid": 2.7916211293260473,
        "astConfTop": 3.4080824940612664,
        "rebConfFloor": 2.5090183335309786,
        "rebConfMid": 3.3744990892531876,
        "rebConfTop": 4.239979844975397,
        "team": "NOP",
        "fanduel_pts": 0,
        "fanduel_reb": 0,
        "fanduel_ast": 0,
        "fanduel_threes": 0,
        "fanduel_blk": 0,
        "fanduel_stl": 0,
        "pick_pts": "OVER",
        "pick_reb": "OVER",
        "pick_ast": "OVER",
        "pick_3s": "OVER",
        "pick_blk": "OVER",
        "pick_stl": "OVER"
    },
    "Zion Williamson": {
        "MIN": 30.201610545449924,
        "FGM": 8.654906493732243,
        "FGA": 15.281823772444199,
        "FG3M": 0.04503849774890098,
        "FG3A": 0.0681514867607621,
        "REB": 6.281677901565553,
        "AST": 4.988173081894407,
        "STL": 0.5687988426425064,
        "BLK": 0.2920808905120967,
        "PF": 2.32509776243926,
        "PTS": 21.354795453475685,
        "FTA": 6.1524481558114665,
        "FTM": 3.847751781400825,
        "FG_PCT": 0.5443020913735436,
        "FG3_PCT": 0.0566658242260654,
        "FT_PCT": 0.5036172174591717,
        "ptsConfFloor": 20.82422414133768,
        "ptsConfMid": 24.270707070707072,
        "ptsConfTop": 27.71719000007646,
        "astConfFloor": 4.0954968888715095,
        "astConfMid": 5.452525252525252,
        "astConfTop": 6.809553616178995,
        "rebConfFloor": 5.69352007597582,
        "rebConfMid": 6.842424242424243,
        "rebConfTop": 7.991328408872666,
        "team": "NOP",
        "fanduel_pts": 0,
        "fanduel_reb": 0,
        "fanduel_ast": 0,
        "fanduel_threes": 0,
        "fanduel_blk": 0,
        "fanduel_stl": 0,
        "pick_pts": "OVER",
        "pick_reb": "OVER",
        "pick_ast": "OVER",
        "pick_3s": "OVER",
        "pick_blk": "OVER",
        "pick_stl": "OVER"
    },
    "Jonas Valanciunas": {
        "MIN": 25.299492877689506,
        "FGM": 4.979391384683567,
        "FGA": 8.855178113331284,
        "FG3M": 0.6813560023105796,
        "FG3A": 1.892199173055704,
        "REB": 9.403508984180379,
        "AST": 1.6916131050971006,
        "STL": 0.42783758164019714,
        "BLK": 1.0581919652795615,
        "PF": 2.5267770891661416,
        "PTS": 11.481779907349686,
        "FTA": 2.8604531747823687,
        "FTM": 2.2375206648076653,
        "FG_PCT": 0.5619213583436873,
        "FG3_PCT": 0.3075579109072434,
        "FT_PCT": 0.6138222424102405,
        "ptsConfFloor": 7.590651001900586,
        "ptsConfMid": 9.325252525252525,
        "ptsConfTop": 11.059854048604464,
        "astConfFloor": 1.1268675980967948,
        "astConfMid": 1.6060606060606062,
        "astConfTop": 2.0852536140244173,
        "rebConfFloor": 7.776112704531059,
        "rebConfMid": 8.914141414141413,
        "rebConfTop": 10.05217012375177,
        "team": "NOP",
        "fanduel_pts": 0,
        "fanduel_reb": 0,
        "fanduel_ast": 0,
        "fanduel_threes": 0,
        "fanduel_blk": 0,
        "fanduel_stl": 0,
        "pick_pts": "OVER",
        "pick_reb": "OVER",
        "pick_ast": "OVER",
        "pick_3s": "OVER",
        "pick_blk": "OVER",
        "pick_stl": "OVER"
    },
    "Dennis Schroder": {
        "MIN": 30.907366357788476,
        "FGM": 5.062846519429381,
        "FGA": 10.952404857822229,
        "FG3M": 1.976535646518089,
        "FG3A": 4.815700366199513,
        "REB": 2.9154927807656237,
        "AST": 6.0215473358086165,
        "STL": 0.8841420417415379,
        "BLK": 0.1190147327527721,
        "PF": 1.9547283144542185,
        "PTS": 14.703695038677381,
        "FTA": 2.3018823550920646,
        "FTM": 2.0168071094021647,
        "FG_PCT": 0.40970283856223483,
        "FG3_PCT": 0.4123114756740873,
        "FT_PCT": 0.5834483330987446,
        "ptsConfFloor": 12.315812402459139,
        "ptsConfMid": 15.643434343434345,
        "ptsConfTop": 18.97105628440955,
        "astConfFloor": 4.9923905876672,
        "astConfMid": 6.165656565656565,
        "astConfTop": 7.338922543645931,
        "rebConfFloor": 1.68739875198053,
        "rebConfMid": 2.625252525252525,
        "rebConfTop": 3.56310629852452,
        "team": "BKN",
        "fanduel_pts": 13.5,
        "fanduel_reb": 2.5,
        "fanduel_ast": 6.5,
        "fanduel_threes": 1.5,
        "fanduel_blk": 0,
        "fanduel_stl": 0,
        "pick_pts": "OVER",
        "pick_reb": "OVER",
        "pick_ast": "UNDER",
        "pick_3s": "OVER",
        "pick_blk": "OVER",
        "pick_stl": "OVER"
    },
    "Kris Murray": "N/A",
    "Toumani Camara": "N/A",
    "Deandre Ayton": {
        "MIN": 30.81624845601354,
        "FGM": 6.314278785861685,
        "FGA": 11.16679348653173,
        "FG3M": 0.05782864521472551,
        "FG3A": 0.1721337819844283,
        "REB": 11.50692285429233,
        "AST": 1.4569458179691614,
        "STL": 1.283715416787815,
        "BLK": 0.7115353998876194,
        "PF": 2.4188469076703574,
        "PTS": 14.88561683548085,
        "FTA": 1.0024956945118781,
        "FTM": 1.076796949607549,
        "FG_PCT": 0.5535402198893333,
        "FG3_PCT": 0.021492166578629478,
        "FT_PCT": 0.3090885196148483,
        "ptsConfFloor": 16.72083505691963,
        "ptsConfMid": 20.7010101010101,
        "ptsConfTop": 24.681185145100574,
        "astConfFloor": 1.0453916553598444,
        "astConfMid": 1.4565656565656566,
        "astConfTop": 1.8677396577714689,
        "rebConfFloor": 10.89499937616076,
        "rebConfMid": 12.934343434343434,
        "rebConfTop": 14.97368749252611,
        "team": "POR",
        "fanduel_pts": 19.5,
        "fanduel_reb": 11.5,
        "fanduel_ast": 0,
        "fanduel_threes": 0,
        "fanduel_blk": 1.5,
        "fanduel_stl": 0,
        "pick_pts": "UNDER",
        "pick_reb": "OVER",
        "pick_ast": "OVER",
        "pick_3s": "OVER",
        "pick_blk": "UNDER",
        "pick_stl": "OVER"
    },
    "CJ McCollum": {
        "MIN": 30.65479021635806,
        "FGM": 7.004746166657553,
        "FGA": 14.697491291070087,
        "FG3M": 3.5734280782660566,
        "FG3A": 7.789555103757763,
        "REB": 4.55845401984819,
        "AST": 3.448558274858849,
        "STL": 1.019186610485472,
        "BLK": 0.9518278314676809,
        "PF": 1.8309777213298974,
        "PTS": 17.184554099534353,
        "FTA": 1.6994259100050422,
        "FTM": 1.6358801808504222,
        "FG_PCT": 0.4437410099674835,
        "FG3_PCT": 0.40290379531164955,
        "FT_PCT": 0.607218854350413,
        "ptsConfFloor": 12.554520187112894,
        "ptsConfMid": 15.291111111111112,
        "ptsConfTop": 18.02770203510933,
        "astConfFloor": 2.5867063131744055,
        "astConfMid": 3.382222222222223,
        "astConfTop": 4.17773813127004,
        "rebConfFloor": 3.716815301208957,
        "rebConfMid": 4.322222222222223,
        "rebConfTop": 4.927629143235488,
        "team": "NOP",
        "fanduel_pts": 0,
        "fanduel_reb": 0,
        "fanduel_ast": 0,
        "fanduel_threes": 0,
        "fanduel_blk": 0,
        "fanduel_stl": 0,
        "pick_pts": "OVER",
        "pick_reb": "OVER",
        "pick_ast": "OVER",
        "pick_3s": "OVER",
        "pick_blk": "OVER",
        "pick_stl": "OVER"
    },
    "DeMar DeRozan": {
        "MIN": 37.400635071966285,
        "FGM": 7.786661752882701,
        "FGA": 17.10344832543199,
        "FG3M": 0.9202688626748708,
        "FG3A": 2.897902067146587,
        "REB": 4.997199225427211,
        "AST": 4.85723670702852,
        "STL": 0.9203324295724111,
        "BLK": 0.8142054000854209,
        "PF": 2.103835571726834,
        "PTS": 26.126436315203286,
        "FTA": 7.595224860329577,
        "FTM": 6.351599645357281,
        "FG_PCT": 0.4785265997089267,
        "FG3_PCT": 0.2876748424998246,
        "FT_PCT": 0.856404398303854,
        "ptsConfFloor": 20.769178415963818,
        "ptsConfMid": 25.685470085470087,
        "ptsConfTop": 30.601761754976348,
        "astConfFloor": 3.793159748858491,
        "astConfMid": 5.042735042735043,
        "astConfTop": 6.292310336611595,
        "rebConfFloor": 3.952582208104713,
        "rebConfMid": 5.218803418803419,
        "rebConfTop": 6.485024629502125,
        "team": "CHI",
        "fanduel_pts": 26.5,
        "fanduel_reb": 5.5,
        "fanduel_ast": 5.5,
        "fanduel_threes": 1.5,
        "fanduel_blk": 0,
        "fanduel_stl": 0.5,
        "pick_pts": "UNDER",
        "pick_reb": "UNDER",
        "pick_ast": "UNDER",
        "pick_3s": "UNDER",
        "pick_blk": "OVER",
        "pick_stl": "OVER"
    },
    "Torrey Craig": {
        "MIN": 20.58844948612337,
        "FGM": 2.2299159733722105,
        "FGA": 5.315023774303356,
        "FG3M": 1.1140684688975602,
        "FG3A": 2.873696038379631,
        "REB": 3.972716487969455,
        "AST": 0.980378676395145,
        "STL": 0.6512127119095376,
        "BLK": 0.35203295585440414,
        "PF": 2.4428525458907853,
        "PTS": 6.483902203225869,
        "FTA": 0.9534396919780102,
        "FTM": 0.5533590514543912,
        "FG_PCT": 0.43953210138030735,
        "FG3_PCT": 0.3231917910614166,
        "FT_PCT": 0.3149552301409399,
        "ptsConfFloor": 3.5390881318752236,
        "ptsConfMid": 5.933333333333334,
        "ptsConfTop": 8.327578534791442,
        "astConfFloor": 0.4946792279718341,
        "astConfMid": 1.0263157894736843,
        "astConfTop": 1.5579523509755344,
        "rebConfFloor": 2.7858417009390446,
        "rebConfMid": 3.842105263157895,
        "rebConfTop": 4.898368825376745,
        "team": "CHI",
        "fanduel_pts": 9.5,
        "fanduel_reb": 6.5,
        "fanduel_ast": 0,
        "fanduel_threes": 1.5,
        "fanduel_blk": 0,
        "fanduel_stl": 0,
        "pick_pts": "UNDER",
        "pick_reb": "UNDER",
        "pick_ast": "OVER",
        "pick_3s": "UNDER",
        "pick_blk": "OVER",
        "pick_stl": "OVER"
    },
    "Nikola Vucevic": {
        "MIN": 34.52756602914127,
        "FGM": 8.266836760724106,
        "FGA": 15.785394296501604,
        "FG3M": 1.1748602942645716,
        "FG3A": 4.2997790797135025,
        "REB": 11.632943637497267,
        "AST": 3.1357260816978823,
        "STL": 0.7439312553843532,
        "BLK": 0.9031049330977482,
        "PF": 2.753898454089503,
        "PTS": 18.33220924648962,
        "FTA": 1.7912492902793697,
        "FTM": 1.4901450872541788,
        "FG_PCT": 0.4646121835947251,
        "FG3_PCT": 0.21772370068164631,
        "FT_PCT": 0.4727956336337499,
        "ptsConfFloor": 15.781691857248907,
        "ptsConfMid": 19.283512544802868,
        "ptsConfTop": 22.78533323235683,
        "astConfFloor": 2.53236112664176,
        "astConfMid": 3.2017921146953405,
        "astConfTop": 3.871223102748921,
        "rebConfFloor": 8.916708853631187,
        "rebConfMid": 10.293189964157706,
        "rebConfTop": 11.669671074684224,
        "team": "CHI",
        "fanduel_pts": 22.5,
        "fanduel_reb": 11.5,
        "fanduel_ast": 3.5,
        "fanduel_threes": 1.5,
        "fanduel_blk": 0,
        "fanduel_stl": 0,
        "pick_pts": "UNDER",
        "pick_reb": "OVER",
        "pick_ast": "UNDER",
        "pick_3s": "UNDER",
        "pick_blk": "OVER",
        "pick_stl": "OVER"
    },
    "Coby White": {
        "MIN": 37.37456686243254,
        "FGM": 6.938347375513699,
        "FGA": 15.103297137951172,
        "FG3M": 3.0692565958176217,
        "FG3A": 7.859081649045883,
        "REB": 4.932440375228818,
        "AST": 4.7022922748842735,
        "STL": 0.5956587488341246,
        "BLK": 0.24815687726374117,
        "PF": 2.561757010868905,
        "PTS": 20.653635482952684,
        "FTA": 4.042596819420924,
        "FTM": 3.2689070289497844,
        "FG_PCT": 0.4304741899215588,
        "FG3_PCT": 0.3302021022471261,
        "FT_PCT": 0.7300794925769867,
        "ptsConfFloor": 16.43467248134526,
        "ptsConfMid": 19.144444444444446,
        "ptsConfTop": 21.85421640754363,
        "astConfFloor": 3.792261267584974,
        "astConfMid": 4.937373737373737,
        "astConfTop": 6.082486207162501,
        "rebConfFloor": 3.8039058085708795,
        "rebConfMid": 4.57070707070707,
        "rebConfTop": 5.337508332843263
    },
    "Shai Gilgeous-Alexander": {
        "MIN": 33.781845210931685,
        "FGM": 11.384153418616021,
        "FGA": 20.216375535663218,
        "FG3M": 1.3935460711369367,
        "FG3A": 3.873167619851106,
        "REB": 5.518017618769361,
        "AST": 5.838739941472319,
        "STL": 2.4994277070493407,
        "BLK": 0.719807658353805,
        "PF": 2.1731936680900312,
        "PTS": 29.34828300692547,
        "FTA": 7.851347609465554,
        "FTM": 7.157636096344923,
        "FG_PCT": 0.5483865967572014,
        "FG3_PCT": 0.4172751973177062,
        "FT_PCT": 0.903226854906249,
        "ptsConfFloor": 28.66957201826172,
        "ptsConfMid": 31.275213675213678,
        "ptsConfTop": 33.88085533216563,
        "astConfFloor": 5.340262929113625,
        "astConfMid": 5.866666666666667,
        "astConfTop": 6.393070404219709,
        "rebConfFloor": 4.322142037608418,
        "rebConfMid": 5.726495726495727,
        "rebConfTop": 7.130849415383036,
        "team": "OKC",
        "fanduel_pts": 30.5,
        "fanduel_reb": 5.5,
        "fanduel_ast": 5.5,
        "fanduel_threes": 1.5,
        "fanduel_blk": 0.5,
        "fanduel_stl": 1.5,
        "pick_pts": "UNDER",
        "pick_reb": "OVER",
        "pick_ast": "OVER",
        "pick_3s": "UNDER",
        "pick_blk": "OVER",
        "pick_stl": "OVER"
    },
    "Bilal Coulibaly": "N/A",
    "Deni Avdija": {
        "MIN": 26.51724993004071,
        "FGM": 6.550527358844731,
        "FGA": 10.03758095584778,
        "FG3M": 1.1373437897370617,
        "FG3A": 2.6025710848011347,
        "REB": 7.31595044514207,
        "AST": 2.743405755390874,
        "STL": 0.7152380117889657,
        "BLK": 0.5790342917312195,
        "PF": 2.3014682750475757,
        "PTS": 14.141726620512888,
        "FTA": 2.9030680960203425,
        "FTM": 2.005051289532114,
        "FG_PCT": 0.5337354724550317,
        "FG3_PCT": 0.33609874532844636,
        "FT_PCT": 0.6754549503784428,
        "ptsConfFloor": 14.251275383339603,
        "ptsConfMid": 16.83915343915344,
        "ptsConfTop": 19.427031494967274,
        "astConfFloor": 2.3765749867541195,
        "astConfMid": 3.0888888888888886,
        "astConfTop": 3.8012027910236585,
        "rebConfFloor": 6.532974457127328,
        "rebConfMid": 8.246560846560847,
        "rebConfTop": 9.960147235994365,
        "team": "WAS",
        "fanduel_pts": 15.5,
        "fanduel_reb": 8.5,
        "fanduel_ast": 4.5,
        "fanduel_threes": 0,
        "fanduel_blk": 0,
        "fanduel_stl": 0,
        "pick_pts": "UNDER",
        "pick_reb": "UNDER",
        "pick_ast": "UNDER",
        "pick_3s": "OVER",
        "pick_blk": "OVER",
        "pick_stl": "OVER"
    },
    "Kyle Kuzma": {
        "MIN": 30.94095021926003,
        "FGM": 9.368452616321463,
        "FGA": 18.73219526309263,
        "FG3M": 2.2965733082106476,
        "FG3A": 6.682762789870232,
        "REB": 6.751459230959609,
        "AST": 3.8006496017304796,
        "STL": 0.39070726821742985,
        "BLK": 0.49951578249149975,
        "PF": 2.1993008420191407,
        "PTS": 24.19187732193258,
        "FTA": 3.599993870201257,
        "FTM": 2.6327275122204346,
        "FG_PCT": 0.4728136415349051,
        "FG3_PCT": 0.3283836369004243,
        "FT_PCT": 0.7375822764524343,
        "ptsConfFloor": 22.400063024141307,
        "ptsConfMid": 24.46597222222222,
        "ptsConfTop": 26.531881420303137,
        "astConfFloor": 3.2957897030163097,
        "astConfMid": 4.385416666666667,
        "astConfTop": 5.475043630317022,
        "rebConfFloor": 5.374681276687764,
        "rebConfMid": 6.5993055555555555,
        "rebConfTop": 7.823929834423346,
        "team": "WAS",
        "fanduel_pts": 23.5,
        "fanduel_reb": 7.5,
        "fanduel_ast": 4.5,
        "fanduel_threes": 2.5,
        "fanduel_blk": 0,
        "fanduel_stl": 0.5,
        "pick_pts": "OVER",
        "pick_reb": "UNDER",
        "pick_ast": "UNDER",
        "pick_3s": "UNDER",
        "pick_blk": "OVER",
        "pick_stl": "UNDER"
    },
    "Richaun Holmes": {
        "MIN": 10.5165040420632,
        "FGM": 1.4423715032760547,
        "FGA": 2.1998095718866124,
        "FG3M": -0.029575481542733206,
        "FG3A": -0.028906290995181716,
        "REB": 3.95843403883576,
        "AST": 0.5770696819996769,
        "STL": 0.22483894814658362,
        "BLK": 0.43931538363778305,
        "PF": 1.5067350837959583,
        "PTS": -1,
        "FTA": 0.7040202388205568,
        "FTM": 0.8805606575177893,
        "FG_PCT": 0.5469927981082678,
        "FG3_PCT": -0.006159828142092913,
        "FT_PCT": 0.19795998698164538,
        "ptsConfFloor": 2.784070459530858,
        "ptsConfMid": 5.4505050505050505,
        "ptsConfTop": 8.116939641479242,
        "astConfFloor": 0.17806031810852527,
        "astConfMid": 0.6141414141414141,
        "astConfTop": 1.0502225101743028,
        "rebConfFloor": 2.401031133830715,
        "rebConfMid": 4.048484848484848,
        "rebConfTop": 5.695938563138982
    },
    "Alex Caruso": {
        "MIN": 27.381159241127797,
        "FGM": 3.159498233889656,
        "FGA": 7.693784902173477,
        "FG3M": 2.0023828651870472,
        "FG3A": 4.612462680603652,
        "REB": 4.637095719362253,
        "AST": 4.094387213627134,
        "STL": 1.4775038298001797,
        "BLK": 1.0231015134613142,
        "PF": 2.4659666799587385,
        "PTS": 9.254372270071608,
        "FTA": 1.8486075002446727,
        "FTM": 1.2579240313610418,
        "FG_PCT": 0.48036794257011645,
        "FG3_PCT": 0.39879030318739156,
        "FT_PCT": 0.36639098068045595,
        "ptsConfFloor": 7.043330208682714,
        "ptsConfMid": 10.231417624521074,
        "ptsConfTop": 13.419505040359432,
        "astConfFloor": 2.973252710980235,
        "astConfMid": 3.934099616858237,
        "astConfTop": 4.89494652273624,
        "rebConfFloor": 2.9796533159219334,
        "rebConfMid": 4.030651340996169,
        "rebConfTop": 5.081649366070405,
        "team": "CHI",
        "fanduel_pts": 13.5,
        "fanduel_reb": 4.5,
        "fanduel_ast": 4.5,
        "fanduel_threes": 1.5,
        "fanduel_blk": 0,
        "fanduel_stl": 2.5,
        "pick_pts": "UNDER",
        "pick_reb": "OVER",
        "pick_ast": "UNDER",
        "pick_3s": "OVER",
        "pick_blk": "OVER",
        "pick_stl": "UNDER"
    },
    "Tyrese Haliburton": {
        "MIN": 33.60554341973327,
        "FGM": 6.669252608246377,
        "FGA": 16.001083757795133,
        "FG3M": 2.6051724934856333,
        "FG3A": 8.307514895252739,
        "REB": 3.7376509497249,
        "AST": 11.538090892110013,
        "STL": 0.9196872527473925,
        "BLK": 0.5759031309721211,
        "PF": 0.9645796440348486,
        "PTS": 20.211811658744438,
        "FTA": 3.256390480387836,
        "FTM": 3.0597566958611484,
        "FG_PCT": 0.4586302165041488,
        "FG3_PCT": 0.33699288531445065,
        "FT_PCT": 0.7063096504002533,
        "ptsConfFloor": 16.539356372450637,
        "ptsConfMid": 18.644444444444446,
        "ptsConfTop": 20.749532516438254,
        "astConfFloor": 9.911453667394216,
        "astConfMid": 11.190123456790124,
        "astConfTop": 12.46879324618603,
        "rebConfFloor": 3.1305866894540664,
        "rebConfMid": 4.0172839506172835,
        "rebConfTop": 4.903981211780501,
        "team": "IND",
        "fanduel_pts": 19.5,
        "fanduel_reb": 3.5,
        "fanduel_ast": 10.5,
        "fanduel_threes": 2.5,
        "fanduel_blk": 0,
        "fanduel_stl": 0.5,
        "pick_pts": "OVER",
        "pick_reb": "OVER",
        "pick_ast": "OVER",
        "pick_3s": "OVER",
        "pick_blk": "OVER",
        "pick_stl": "OVER"
    },
    "Klay Thompson": {
        "MIN": 28.616248439415067,
        "FGM": 5.506843290993302,
        "FGA": 13.030551975731889,
        "FG3M": 2.886676628875013,
        "FG3A": 7.894846255117371,
        "REB": 3.1837694856917627,
        "AST": 2.313914634569507,
        "STL": 0.5843809313789989,
        "BLK": 0.44384667678483547,
        "PF": 1.8897544471372603,
        "PTS": 16.77205064795708,
        "FTA": 1.7234603363070242,
        "FTM": 1.710641083828508,
        "FG_PCT": 0.39801189014660676,
        "FG3_PCT": 0.3115087827206161,
        "FT_PCT": 0.6769037057639458,
        "ptsConfFloor": 13.642680606538713,
        "ptsConfMid": 17.616129032258062,
        "ptsConfTop": 21.589577457977413,
        "astConfFloor": 1.2019221051060116,
        "astConfMid": 1.8928315412186378,
        "astConfTop": 2.5837409773312645,
        "rebConfFloor": 2.345783178874882,
        "rebConfMid": 2.9788530465949825,
        "rebConfTop": 3.611922914315082
    },
    "Josh Giddey": {
        "MIN": 23.601839383289693,
        "FGM": 3.4118848925875827,
        "FGA": 9.48253244888771,
        "FG3M": 0.8964720180517459,
        "FG3A": 2.6745420817184358,
        "REB": 6.129250678553148,
        "AST": 4.0182934331639855,
        "STL": 0.5904979268882866,
        "BLK": 0.6077823619599895,
        "PF": 1.298714258062751,
        "PTS": 10.394082752141554,
        "FTA": 0.99025690320241,
        "FTM": 0.8615090134285092,
        "FG_PCT": 0.4634161090414615,
        "FG3_PCT": 0.24958121884860168,
        "FT_PCT": 0.4350902383736083,
        "ptsConfFloor": 11.09784776102758,
        "ptsConfMid": 12.895726495726494,
        "ptsConfTop": 14.69360523042541,
        "astConfFloor": 3.7005649940552345,
        "astConfMid": 4.444444444444445,
        "astConfTop": 5.188323894833655,
        "rebConfFloor": 5.009402325264802,
        "rebConfMid": 6.225641025641025,
        "rebConfTop": 7.441879726017249,
        "team": "OKC",
        "fanduel_pts": 10.5,
        "fanduel_reb": 6.5,
        "fanduel_ast": 4.5,
        "fanduel_threes": 0,
        "fanduel_blk": 0,
        "fanduel_stl": 0,
        "pick_pts": "UNDER",
        "pick_reb": "UNDER",
        "pick_ast": "UNDER",
        "pick_3s": "OVER",
        "pick_blk": "OVER",
        "pick_stl": "OVER"
    },
    "Luguentz Dort": {
        "MIN": 27.358170422133746,
        "FGM": 4.153432977901631,
        "FGA": 7.429764849268551,
        "FG3M": 2.2058333089547433,
        "FG3A": 4.490074160186913,
        "REB": 3.4575314750463577,
        "AST": 1.6011324825561333,
        "STL": 1.1144204375671771,
        "BLK": 0.8429449426881126,
        "PF": 3.0644227134386095,
        "PTS": 10.292111764622442,
        "FTA": 1.286630984260049,
        "FTM": 1.1881084634744352,
        "FG_PCT": 0.4510812640350921,
        "FG3_PCT": 0.4048869691001083,
        "FT_PCT": 0.3613047358154961,
        "ptsConfFloor": 9.134283403802671,
        "ptsConfMid": 11.375347222222222,
        "ptsConfTop": 13.616411040641772,
        "astConfFloor": 0.9276433753750295,
        "astConfMid": 1.5145833333333334,
        "astConfTop": 2.1015232912916373,
        "rebConfFloor": 2.0258798756781298,
        "rebConfMid": 3.157291666666667,
        "rebConfTop": 4.288703457655203,
        "team": "OKC",
        "fanduel_pts": 10.5,
        "fanduel_reb": 0,
        "fanduel_ast": 0,
        "fanduel_threes": 2.5,
        "fanduel_blk": 0,
        "fanduel_stl": 1.5,
        "pick_pts": "UNDER",
        "pick_reb": "OVER",
        "pick_ast": "OVER",
        "pick_3s": "UNDER",
        "pick_blk": "OVER",
        "pick_stl": "UNDER"
    },
    "Jalen Williams": {
        "MIN": 31.444722205614706,
        "FGM": 7.7813136330544,
        "FGA": 13.35908690761481,
        "FG3M": 1.4039200843500768,
        "FG3A": 3.390350537090848,
        "REB": 3.742508483353031,
        "AST": 3.8265930846557734,
        "STL": 0.7476677072589488,
        "BLK": 0.5157441563932361,
        "PF": 2.7792831820356856,
        "PTS": 19.12920792439792,
        "FTA": 2.730218529347186,
        "FTM": 2.9554262113382457,
        "FG_PCT": 0.5818790508577826,
        "FG3_PCT": 0.42577681523275046,
        "FT_PCT": 0.6637089967200338,
        "ptsConfFloor": 14.49709863346281,
        "ptsConfMid": 19.078719397363464,
        "ptsConfTop": 23.660340161264116,
        "astConfFloor": 3.580729640525673,
        "astConfMid": 4.208286252354049,
        "astConfTop": 4.835842864182425,
        "rebConfFloor": 3.10541921367053,
        "rebConfMid": 3.805649717514124,
        "rebConfTop": 4.505880221357718,
        "team": "OKC",
        "fanduel_pts": 18.5,
        "fanduel_reb": 3.5,
        "fanduel_ast": 4.5,
        "fanduel_threes": 1.5,
        "fanduel_blk": 0.5,
        "fanduel_stl": 1.5,
        "pick_pts": "OVER",
        "pick_reb": "OVER",
        "pick_ast": "UNDER",
        "pick_3s": "UNDER",
        "pick_blk": "OVER",
        "pick_stl": "UNDER"
    },
    "Chet Holmgren": "N/A",
    "John Konchar": {
        "MIN": 21.374476042853537,
        "FGM": 2.1240638975308976,
        "FGA": 4.367357900179483,
        "FG3M": 0.9800435313177644,
        "FG3A": 2.8707642981626806,
        "REB": 5.418291509415878,
        "AST": 2.3077359857166178,
        "STL": 0.7477899212089004,
        "BLK": 1.0896709914293172,
        "PF": 1.22479448831668,
        "PTS": 5.563042420804523,
        "FTA": 0.4884789790097872,
        "FTM": 0.29713157386217665,
        "FG_PCT": 0.36132935616441575,
        "FG3_PCT": 0.30197531874421446,
        "FT_PCT": 0.18045482894726309,
        "ptsConfFloor": 3.8069662791117778,
        "ptsConfMid": 5.598692810457517,
        "ptsConfTop": 7.3904193418032555,
        "astConfFloor": 1.8874053361105585,
        "astConfMid": 2.522875816993464,
        "astConfTop": 3.1583462978763692,
        "rebConfFloor": 4.6728676347641445,
        "rebConfMid": 5.967320261437909,
        "rebConfTop": 7.261772888111673
    },
    "Austin Reaves": {
        "MIN": 29.71224813229915,
        "FGM": 6.071150578714605,
        "FGA": 11.01392415195335,
        "FG3M": 1.5270929184525879,
        "FG3A": 4.959588292746784,
        "REB": 4.455256650815195,
        "AST": 5.9242630186165535,
        "STL": 1.110477010751099,
        "BLK": 0.15140522947644885,
        "PF": 1.6106582536742253,
        "PTS": 14.912819392874628,
        "FTA": 2.412331600085178,
        "FTM": 2.0181225824193714,
        "FG_PCT": 0.48781585737213995,
        "FG3_PCT": 0.33295623774304617,
        "FT_PCT": 0.794981670333575,
        "ptsConfFloor": 15.492617253395096,
        "ptsConfMid": 17.740630182421228,
        "ptsConfTop": 19.988643111447356,
        "astConfFloor": 4.6551690389655205,
        "astConfMid": 5.640796019900498,
        "astConfTop": 6.626423000835476,
        "rebConfFloor": 4.0575236048980825,
        "rebConfMid": 4.701492537313433,
        "rebConfTop": 5.345461469728783,
        "team": "LAL",
        "fanduel_pts": 16.5,
        "fanduel_reb": 4.5,
        "fanduel_ast": 5.5,
        "fanduel_threes": 2.5,
        "fanduel_blk": 0,
        "fanduel_stl": 0,
        "pick_pts": "UNDER",
        "pick_reb": "UNDER",
        "pick_ast": "OVER",
        "pick_3s": "UNDER",
        "pick_blk": "OVER",
        "pick_stl": "OVER"
    },
    "Rui Hachimura": {
        "MIN": 25.291134697605603,
        "FGM": 5.944876848951303,
        "FGA": 9.376422321881288,
        "FG3M": 1.3932975612285055,
        "FG3A": 3.55145122790663,
        "REB": 3.6624116116055534,
        "AST": 1.0236080777108683,
        "STL": 0.8549051061662027,
        "BLK": 0.2832808022542858,
        "PF": 1.385963266603417,
        "PTS": 12.755101810319761,
        "FTA": 2.2363507252888137,
        "FTM": 1.6595364097421172,
        "FG_PCT": 0.5584173946687845,
        "FG3_PCT": 0.4402175917640904,
        "FT_PCT": 0.44216914193677587,
        "ptsConfFloor": 11.31100537061378,
        "ptsConfMid": 15.159748427672957,
        "ptsConfTop": 19.008491484732133,
        "astConfFloor": 0.6681874205747752,
        "astConfMid": 1.1584905660377358,
        "astConfTop": 1.6487937115006963,
        "rebConfFloor": 2.5748683524134814,
        "rebConfMid": 3.3438155136268346,
        "rebConfTop": 4.112762674840187,
        "team": "LAL",
        "fanduel_pts": 14.5,
        "fanduel_reb": 4.5,
        "fanduel_ast": 0,
        "fanduel_threes": 1.5,
        "fanduel_blk": 0,
        "fanduel_stl": 0,
        "pick_pts": "UNDER",
        "pick_reb": "UNDER",
        "pick_ast": "OVER",
        "pick_3s": "UNDER",
        "pick_blk": "OVER",
        "pick_stl": "OVER"
    },
    "Mike Conley": {
        "MIN": 28.4992952294176,
        "FGM": 3.207219767746001,
        "FGA": 7.893483752500942,
        "FG3M": 2.2835325474949935,
        "FG3A": 4.767547607663833,
        "REB": 3.3550110690862747,
        "AST": 5.758479159933655,
        "STL": 0.9840948763195596,
        "BLK": 0.15344170244967684,
        "PF": 1.737477073125133,
        "PTS": 9.106369566477449,
        "FTA": 1.1423954651671786,
        "FTM": 0.8282649007530498,
        "FG_PCT": 0.42122725478314044,
        "FG3_PCT": 0.4546955312640656,
        "FT_PCT": 0.40898089617139327,
        "ptsConfFloor": 8.378273986969335,
        "ptsConfMid": 11.535154826958106,
        "ptsConfTop": 14.692035666946877,
        "astConfFloor": 4.518763912956733,
        "astConfMid": 5.3938069216757745,
        "astConfTop": 6.268849930394815,
        "rebConfFloor": 2.6244410139519108,
        "rebConfMid": 3.2280510018214934,
        "rebConfTop": 3.831660989691077,
        "team": "MIN",
        "fanduel_pts": 11.5,
        "fanduel_reb": 3.5,
        "fanduel_ast": 6.5,
        "fanduel_threes": 2.5,
        "fanduel_blk": 0,
        "fanduel_stl": 0,
        "pick_pts": "UNDER",
        "pick_reb": "UNDER",
        "pick_ast": "UNDER",
        "pick_3s": "UNDER",
        "pick_blk": "OVER",
        "pick_stl": "OVER"
    },
    "Andrew Wiggins": {
        "MIN": 25.36721296487326,
        "FGM": 4.800466373701831,
        "FGA": 9.606442081646287,
        "FG3M": 0.6599580182565106,
        "FG3A": 2.4444543040642484,
        "REB": 4.324398186850353,
        "AST": 2.0011240311160368,
        "STL": 0.3411005381300299,
        "BLK": 0.3374936644703497,
        "PF": 1.9427159501530364,
        "PTS": 12.032800117253128,
        "FTA": 2.866350676909701,
        "FTM": 1.9980706644078527,
        "FG_PCT": 0.41389046970752275,
        "FG3_PCT": 0.2573976104693737,
        "FT_PCT": 0.49194763603438,
        "ptsConfFloor": 9.500196442970221,
        "ptsConfMid": 12.196428571428571,
        "ptsConfTop": 14.892660699886923,
        "astConfFloor": 1.3638472657079006,
        "astConfMid": 1.7936507936507937,
        "astConfTop": 2.223454321593687,
        "rebConfFloor": 3.05920199487055,
        "rebConfMid": 4.04920634920635,
        "rebConfTop": 5.039210703542149,
        "team": "GSW",
        "fanduel_pts": 11.5,
        "fanduel_reb": 3.5,
        "fanduel_ast": 0,
        "fanduel_threes": 1.5,
        "fanduel_blk": 0,
        "fanduel_stl": 0.5,
        "pick_pts": "OVER",
        "pick_reb": "OVER",
        "pick_ast": "OVER",
        "pick_3s": "UNDER",
        "pick_blk": "OVER",
        "pick_stl": "UNDER"
    },
    "Jonathan Kuminga": {
        "MIN": 25.961643272993268,
        "FGM": 5.344833411889378,
        "FGA": 11.144171050654172,
        "FG3M": 0.5385737099063495,
        "FG3A": 2.3452509401275807,
        "REB": 4.9363388988187005,
        "AST": 2.4165555601462714,
        "STL": 0.6144709393174229,
        "BLK": 0.4311220502770161,
        "PF": 2.3805447773995354,
        "PTS": 14.914909206377153,
        "FTA": 4.5496196473872175,
        "FTM": 2.950513366142756,
        "FG_PCT": 0.4690230565627013,
        "FG3_PCT": 0.1475936848342898,
        "FT_PCT": 0.69165160543028,
        "ptsConfFloor": 16.656591260780086,
        "ptsConfMid": 18.908333333333335,
        "ptsConfTop": 21.160075405886584,
        "astConfFloor": 1.802708471753542,
        "astConfMid": 2.243055555555556,
        "astConfTop": 2.683402639357569,
        "rebConfFloor": 3.8870311182730735,
        "rebConfMid": 5.087847222222222,
        "rebConfTop": 6.288663326171371,
        "team": "GSW",
        "fanduel_pts": 17.5,
        "fanduel_reb": 5.5,
        "fanduel_ast": 0,
        "fanduel_threes": 0,
        "fanduel_blk": 0,
        "fanduel_stl": 0,
        "pick_pts": "UNDER",
        "pick_reb": "UNDER",
        "pick_ast": "OVER",
        "pick_3s": "OVER",
        "pick_blk": "OVER",
        "pick_stl": "OVER"
    },
    "D'Angelo Russell": {
        "MIN": 31.39298447634475,
        "FGM": 7.418270132154339,
        "FGA": 13.855846476365748,
        "FG3M": 2.5735226913134213,
        "FG3A": 6.547329089512423,
        "REB": 3.5212502835766655,
        "AST": 6.583754782285813,
        "STL": 0.8631934455356789,
        "BLK": 0.5708496656619568,
        "PF": 2.152759796130287,
        "PTS": 17.22591534472598,
        "FTA": 2.2898069607220863,
        "FTM": 1.7965664903421665,
        "FG_PCT": 0.4405498699106983,
        "FG3_PCT": 0.3534401526164352,
        "FT_PCT": 0.5985931700319982,
        "ptsConfFloor": 13.47515251669662,
        "ptsConfMid": 19.346236559139786,
        "ptsConfTop": 25.21732060158295,
        "astConfFloor": 4.658447499124487,
        "astConfMid": 5.96415770609319,
        "astConfTop": 7.269867913061893,
        "rebConfFloor": 2.442809781464304,
        "rebConfMid": 3.4505376344086023,
        "rebConfTop": 4.458265487352901,
        "team": "LAL",
        "fanduel_pts": 17.5,
        "fanduel_reb": 3.5,
        "fanduel_ast": 5.5,
        "fanduel_threes": 3.5,
        "fanduel_blk": 0,
        "fanduel_stl": 1.5,
        "pick_pts": "UNDER",
        "pick_reb": "OVER",
        "pick_ast": "OVER",
        "pick_3s": "UNDER",
        "pick_blk": "OVER",
        "pick_stl": "UNDER"
    },
    "Collin Sexton": {
        "MIN": 24.564297946166892,
        "FGM": 6.244501294458608,
        "FGA": 12.131018016723045,
        "FG3M": 1.3854098450619203,
        "FG3A": 4.543212503542216,
        "REB": 2.8058545922003475,
        "AST": 5.237022778413959,
        "STL": 0.8253980245956887,
        "BLK": 0.25454845013199545,
        "PF": 1.7993980375270184,
        "PTS": 18.145868379236507,
        "FTA": 4.734817740662579,
        "FTM": 4.068638340888481,
        "FG_PCT": 0.4583125273724247,
        "FG3_PCT": 0.33050485267605434,
        "FT_PCT": 0.8523891208369326,
        "ptsConfFloor": 18.062984143718953,
        "ptsConfMid": 20.391919191919193,
        "ptsConfTop": 22.720854240119433,
        "astConfFloor": 4.617373510016727,
        "astConfMid": 5.392929292929293,
        "astConfTop": 6.168485075841858,
        "rebConfFloor": 2.1164571001465267,
        "rebConfMid": 3.046464646464646,
        "rebConfTop": 3.9764721927827664,
        "team": "UTA",
        "fanduel_pts": 20.5,
        "fanduel_reb": 3.5,
        "fanduel_ast": 5.5,
        "fanduel_threes": 1.5,
        "fanduel_blk": 0,
        "fanduel_stl": 0.5,
        "pick_pts": "UNDER",
        "pick_reb": "UNDER",
        "pick_ast": "UNDER",
        "pick_3s": "UNDER",
        "pick_blk": "OVER",
        "pick_stl": "OVER"
    },
    "Brice Sensabaugh": "N/A",
    "Taylor Hendricks": "N/A",
    "John Collins": {
        "MIN": 28.985323078322903,
        "FGM": 6.21147068774303,
        "FGA": 11.405841103089811,
        "FG3M": 1.1132602337756707,
        "FG3A": 3.4199981670402555,
        "REB": 9.860789432267886,
        "AST": 1.3133889156946565,
        "STL": 0.5865004229233737,
        "BLK": 1.225048142583893,
        "PF": 2.8749923482783695,
        "PTS": 14.48687416785743,
        "FTA": 2.812994730556679,
        "FTM": 1.879331368227049,
        "FG_PCT": 0.5331090525268268,
        "FG3_PCT": 0.3479054308032096,
        "FT_PCT": 0.6036100467226866,
        "ptsConfFloor": 13.769800844729557,
        "ptsConfMid": 16.204301075268816,
        "ptsConfTop": 18.638801305808077,
        "astConfFloor": 0.7093378220190174,
        "astConfMid": 1.1702508960573477,
        "astConfTop": 1.6311639700956782,
        "rebConfFloor": 7.726774398023832,
        "rebConfMid": 9.627240143369177,
        "rebConfTop": 11.52770588871452,
        "team": "UTA",
        "fanduel_pts": 15.5,
        "fanduel_reb": 9.5,
        "fanduel_ast": 0,
        "fanduel_threes": 1.5,
        "fanduel_blk": 1.5,
        "fanduel_stl": 0,
        "pick_pts": "UNDER",
        "pick_reb": "OVER",
        "pick_ast": "OVER",
        "pick_3s": "UNDER",
        "pick_blk": "UNDER",
        "pick_stl": "OVER"
    },
    "Jalen Brunson": {
        "MIN": 34.41344423437587,
        "FGM": 10.361850798373906,
        "FGA": 20.08647266740539,
        "FG3M": 2.245090347634196,
        "FG3A": 6.48309262469318,
        "REB": 3.174559703700065,
        "AST": 5.364659494981469,
        "STL": 1.0472671645842315,
        "BLK": 0.19022758906572249,
        "PF": 2.0180314277809224,
        "PTS": 26.287538948834616,
        "FTA": 6.015311019980824,
        "FTM": 4.676304552038344,
        "FG_PCT": 0.4586676953217515,
        "FG3_PCT": 0.41072428924363186,
        "FT_PCT": 0.8156730290801241,
        "ptsConfFloor": 19.627398492276622,
        "ptsConfMid": 25.943169398907106,
        "ptsConfTop": 32.258940305537585,
        "astConfFloor": 4.168518648951658,
        "astConfMid": 5.858287795992713,
        "astConfTop": 7.54805694303377,
        "rebConfFloor": 2.1436394883135037,
        "rebConfMid": 2.9187613843351543,
        "rebConfTop": 3.693883280356806,
        "team": "NYK",
        "fanduel_pts": 27.5,
        "fanduel_reb": 3.5,
        "fanduel_ast": 7.5,
        "fanduel_threes": 2.5,
        "fanduel_blk": 0,
        "fanduel_stl": 0,
        "pick_pts": "UNDER",
        "pick_reb": "UNDER",
        "pick_ast": "UNDER",
        "pick_3s": "UNDER",
        "pick_blk": "OVER",
        "pick_stl": "OVER"
    },
    "Anthony Edwards": {
        "MIN": 34.496426095759574,
        "FGM": 9.53640787801152,
        "FGA": 19.342404096382307,
        "FG3M": 2.3996092965227116,
        "FG3A": 6.696642715123107,
        "REB": 5.7737964629245075,
        "AST": 4.9582869940902095,
        "STL": 1.2090502690984368,
        "BLK": 0.37557342818258943,
        "PF": 1.9687282552194982,
        "PTS": 28.706670952031104,
        "FTA": 6.161824611077163,
        "FTM": 6.01032022670408,
        "FG_PCT": 0.4497923816422956,
        "FG3_PCT": 0.3612562452112369,
        "FT_PCT": 0.8566994826730226,
        "ptsConfFloor": 22.25694835220757,
        "ptsConfMid": 27.45925925925926,
        "ptsConfTop": 32.66157016631095,
        "astConfFloor": 3.8330513399702526,
        "astConfMid": 4.766137566137566,
        "astConfTop": 5.6992237923048785,
        "rebConfFloor": 4.694319536451368,
        "rebConfMid": 5.561904761904763,
        "rebConfTop": 6.4294899873581555,
        "team": "MIN",
        "fanduel_pts": 32.5,
        "fanduel_reb": 6.5,
        "fanduel_ast": 4.5,
        "fanduel_threes": 2.5,
        "fanduel_blk": 0.5,
        "fanduel_stl": 1.5,
        "pick_pts": "UNDER",
        "pick_reb": "UNDER",
        "pick_ast": "OVER",
        "pick_3s": "UNDER",
        "pick_blk": "UNDER",
        "pick_stl": "UNDER"
    },
    "Jaden McDaniels": {
        "MIN": 30.628600540669105,
        "FGM": 3.451119844193327,
        "FGA": 8.715581099172375,
        "FG3M": 0.998258185666349,
        "FG3A": 3.2488026124818576,
        "REB": 3.199859478850515,
        "AST": 1.611026760171096,
        "STL": 0.7819364158920564,
        "BLK": 0.5417720008586592,
        "PF": 3.0096960745309587,
        "PTS": 9.6088953048657,
        "FTA": 0.70773870863094,
        "FTM": 0.5458637111246678,
        "FG_PCT": 0.47790557178265547,
        "FG3_PCT": 0.27010431339712554,
        "FT_PCT": 0.31390513701809086,
        "ptsConfFloor": 6.688927689301093,
        "ptsConfMid": 9.284920634920633,
        "ptsConfTop": 11.880913580540176,
        "astConfFloor": 0.8601685059147458,
        "astConfMid": 1.7206349206349207,
        "astConfTop": 2.5811013353550956,
        "rebConfFloor": 3.1467889866813827,
        "rebConfMid": 4.032539682539682,
        "rebConfTop": 4.918290378397983
    },
    "Keyonte George": "N/A",
    "Darius Garland": {
        "MIN": 32.82731106747876,
        "FGM": 6.207626293732509,
        "FGA": 14.130948437142635,
        "FG3M": 2.1407518510422143,
        "FG3A": 6.149838816796379,
        "REB": 2.4605764572834348,
        "AST": 6.94107338518555,
        "STL": 1.3220058157685826,
        "BLK": 0.15532995231430147,
        "PF": 1.1709993826633198,
        "PTS": 19.771237660106884,
        "FTA": 4.501632032594353,
        "FTM": 3.7195315220882414,
        "FG_PCT": 0.4367470987169882,
        "FG3_PCT": 0.29807473096619286,
        "FT_PCT": 0.6687951138344723,
        "ptsConfFloor": 17.160026664425942,
        "ptsConfMid": 21.066666666666666,
        "ptsConfTop": 24.973306668907394,
        "astConfFloor": 5.830803671381375,
        "astConfMid": 6.955555555555556,
        "astConfTop": 8.080307439729737,
        "rebConfFloor": 1.622376732555649,
        "rebConfMid": 2.565079365079365,
        "rebConfTop": 3.507781997603081,
        "team": "CLE",
        "fanduel_pts": 18.5,
        "fanduel_reb": 2.5,
        "fanduel_ast": 5.5,
        "fanduel_threes": 2.5,
        "fanduel_blk": 0,
        "fanduel_stl": 1.5,
        "pick_pts": "OVER",
        "pick_reb": "UNDER",
        "pick_ast": "OVER",
        "pick_3s": "UNDER",
        "pick_blk": "OVER",
        "pick_stl": "UNDER"
    },
    "Harrison Barnes": {
        "MIN": 28.438798177409573,
        "FGM": 3.5947959676377845,
        "FGA": 7.901246181921806,
        "FG3M": 1.7403070920045534,
        "FG3A": 4.826366457771701,
        "REB": 2.5363783585275135,
        "AST": 0.8879854239484515,
        "STL": 0.8076918963086278,
        "BLK": 0.19993306077826137,
        "PF": 1.4565303743361684,
        "PTS": 10.318993648586787,
        "FTA": 1.6984754785315892,
        "FTM": 1.233150237249982,
        "FG_PCT": 0.45761201880570124,
        "FG3_PCT": 0.3648814656522371,
        "FT_PCT": 0.5588323155333119,
        "ptsConfFloor": 10.153952133261233,
        "ptsConfMid": 13.16923076923077,
        "ptsConfTop": 16.184509405200306,
        "astConfFloor": 0.5645831961331483,
        "astConfMid": 1.0683760683760684,
        "astConfTop": 1.5721689406189885,
        "rebConfFloor": 1.4914654744354106,
        "rebConfMid": 2.454700854700855,
        "rebConfTop": 3.4179362349662994,
        "team": "SAC",
        "fanduel_pts": 11.5,
        "fanduel_reb": 2.5,
        "fanduel_ast": 0,
        "fanduel_threes": 1.5,
        "fanduel_blk": 0,
        "fanduel_stl": 0,
        "pick_pts": "UNDER",
        "pick_reb": "OVER",
        "pick_ast": "OVER",
        "pick_3s": "OVER",
        "pick_blk": "OVER",
        "pick_stl": "OVER"
    },
    "Keegan Murray": {
        "MIN": 33.261323244622595,
        "FGM": 5.240693526611461,
        "FGA": 12.337850572638452,
        "FG3M": 2.1276378074574263,
        "FG3A": 5.826736377960538,
        "REB": 4.870273408790955,
        "AST": 1.403015247640862,
        "STL": 1.0979625286964763,
        "BLK": 0.7889030868820307,
        "PF": 2.773060487493925,
        "PTS": 15.583444324268434,
        "FTA": 2.3410407733599423,
        "FTM": 1.783539359458573,
        "FG_PCT": 0.4480709167563574,
        "FG3_PCT": 0.3334530366483998,
        "FT_PCT": 0.5838726849948487,
        "ptsConfFloor": 9.505023623603392,
        "ptsConfMid": 12.633333333333333,
        "ptsConfTop": 15.761643043063273,
        "astConfFloor": 0.97788791724658,
        "astConfMid": 1.7444444444444445,
        "astConfTop": 2.511000971642309,
        "rebConfFloor": 4.1013578947242575,
        "rebConfMid": 5.483333333333333,
        "rebConfTop": 6.865308771942409,
        "team": "SAC",
        "fanduel_pts": 13.5,
        "fanduel_reb": 5.5,
        "fanduel_ast": 0,
        "fanduel_threes": 1.5,
        "fanduel_blk": 0.5,
        "fanduel_stl": 0,
        "pick_pts": "OVER",
        "pick_reb": "UNDER",
        "pick_ast": "OVER",
        "pick_3s": "OVER",
        "pick_blk": "OVER",
        "pick_stl": "OVER"
    },
    "Domantas Sabonis": {
        "MIN": 35.46407594590903,
        "FGM": 8.201562243908555,
        "FGA": 12.158126691980922,
        "FG3M": 0.5314752602682462,
        "FG3A": 1.3205302085821835,
        "REB": 15.126227399847988,
        "AST": 9.37370379741216,
        "STL": 0.9614614673722531,
        "BLK": 0.6983127345313758,
        "PF": 3.2243060213544736,
        "PTS": 17.123230392806818,
        "FTA": 4.79013585860366,
        "FTM": 3.371396404332414,
        "FG_PCT": 0.6132214490598282,
        "FG3_PCT": 0.370865885548581,
        "FT_PCT": 0.6339709660577435,
        "ptsConfFloor": 18.14178801412515,
        "ptsConfMid": 20.953846153846154,
        "ptsConfTop": 23.765904293567157,
        "astConfFloor": 8.138870143961666,
        "astConfMid": 9.104273504273506,
        "astConfTop": 10.069676864585341,
        "rebConfFloor": 13.385080593916994,
        "rebConfMid": 15.039316239316237,
        "rebConfTop": 16.693551884715486,
        "team": "SAC",
        "fanduel_pts": 19.5,
        "fanduel_reb": 13.5,
        "fanduel_ast": 8.5,
        "fanduel_threes": 0,
        "fanduel_blk": 0,
        "fanduel_stl": 1.5,
        "pick_pts": "UNDER",
        "pick_reb": "OVER",
        "pick_ast": "OVER",
        "pick_3s": "OVER",
        "pick_blk": "OVER",
        "pick_stl": "UNDER"
    },
    "Donte DiVincenzo": {
        "MIN": 22.643421702708107,
        "FGM": 6.770788319351036,
        "FGA": 10.307074155046177,
        "FG3M": 2.797462964009026,
        "FG3A": 7.60086035253178,
        "REB": 3.9831941448650277,
        "AST": 3.4782673057786546,
        "STL": 1.3297262761190423,
        "BLK": 0.4161104852502323,
        "PF": 2.2624116446328233,
        "PTS": 15.3627804663493,
        "FTA": 1.4221720065940722,
        "FTM": 1.0705246917522167,
        "FG_PCT": 0.4178976486597276,
        "FG3_PCT": 0.3874241709174894,
        "FT_PCT": 0.26009234672244097,
        "ptsConfFloor": 13.778475496905173,
        "ptsConfMid": 16.336752136752136,
        "ptsConfTop": 18.8950287765991,
        "astConfFloor": 2.808221798920908,
        "astConfMid": 3.516239316239316,
        "astConfTop": 4.224256833557725,
        "rebConfFloor": 3.189260947601321,
        "rebConfMid": 4.235897435897436,
        "rebConfTop": 5.282533924193551,
        "team": "NYK",
        "fanduel_pts": 16.5,
        "fanduel_reb": 4.5,
        "fanduel_ast": 3.5,
        "fanduel_threes": 3.5,
        "fanduel_blk": 0,
        "fanduel_stl": 1.5,
        "pick_pts": "UNDER",
        "pick_reb": "UNDER",
        "pick_ast": "UNDER",
        "pick_3s": "UNDER",
        "pick_blk": "OVER",
        "pick_stl": "UNDER"
    },
    "Josh Hart": {
        "MIN": 31.032391331669977,
        "FGM": 4.447352445753158,
        "FGA": 8.136604384772806,
        "FG3M": 1.1139542104304445,
        "FG3A": 3.0823518983441605,
        "REB": 9.330791078140749,
        "AST": 3.941859226250186,
        "STL": 0.9653830084667303,
        "BLK": 0.1654721634459242,
        "PF": 2.1458735128839272,
        "PTS": 9.753608763866975,
        "FTA": 0.8117658311490297,
        "FTM": 0.6653678661212488,
        "FG_PCT": 0.3729555850588703,
        "FG3_PCT": 0.277226130579614,
        "FT_PCT": 0.31691368386558244,
        "ptsConfFloor": 9.751905702764388,
        "ptsConfMid": 12.425641025641028,
        "ptsConfTop": 15.09937634851766,
        "astConfFloor": 3.2447115535786746,
        "astConfMid": 4.694017094017094,
        "astConfTop": 6.143322634455514,
        "rebConfFloor": 8.225723658986402,
        "rebConfMid": 10.406837606837607,
        "rebConfTop": 12.587951554688814,
        "team": "NYK",
        "fanduel_pts": 12.5,
        "fanduel_reb": 9.5,
        "fanduel_ast": 4.5,
        "fanduel_threes": 1.5,
        "fanduel_blk": 0,
        "fanduel_stl": 1.5,
        "pick_pts": "UNDER",
        "pick_reb": "UNDER",
        "pick_ast": "UNDER",
        "pick_3s": "UNDER",
        "pick_blk": "OVER",
        "pick_stl": "UNDER"
    },
    "Isaiah Hartenstein": {
        "MIN": 24.483547866519626,
        "FGM": 3.5826099560506837,
        "FGA": 4.998753242675248,
        "FG3M": 0.07424740543869315,
        "FG3A": 0.20534647765376568,
        "REB": 8.71403620834101,
        "AST": 3.1355867171980627,
        "STL": 1.0908402823996137,
        "BLK": 0.9328611364693931,
        "PF": 2.67885742349104,
        "PTS": -1,
        "FTA": 1.9063989843907212,
        "FTM": 1.4982241142126198,
        "FG_PCT": 0.6162738662482153,
        "FG3_PCT": 0.044296798782144486,
        "FT_PCT": 0.5270052244408592,
        "ptsConfFloor": 5.267112386342578,
        "ptsConfMid": 6.661111111111111,
        "ptsConfTop": 8.055109835879643,
        "astConfFloor": 1.927014038427151,
        "astConfMid": 2.527777777777778,
        "astConfTop": 3.1285415171284043,
        "rebConfFloor": 6.508713056194035,
        "rebConfMid": 7.955555555555556,
        "rebConfTop": 9.402398054917077,
        "team": "NYK",
        "fanduel_pts": 6.5,
        "fanduel_reb": 7.5,
        "fanduel_ast": 0,
        "fanduel_threes": 0,
        "fanduel_blk": 0.5,
        "fanduel_stl": 0,
        "pick_pts": "UNDER",
        "pick_reb": "OVER",
        "pick_ast": "OVER",
        "pick_3s": "OVER",
        "pick_blk": "OVER",
        "pick_stl": "OVER"
    },
    "De'Aaron Fox": {
        "MIN": 36.28665858649491,
        "FGM": 9.265978986011195,
        "FGA": 21.437545648629044,
        "FG3M": 3.3454275334361006,
        "FG3A": 8.03766384931326,
        "REB": 4.878216993334819,
        "AST": 5.395435022881725,
        "STL": 2.1016865084383234,
        "BLK": 0.3623704987856016,
        "PF": 2.8183792830826215,
        "PTS": 27.964688886294667,
        "FTA": 6.591537256019376,
        "FTM": 3.888601060713939,
        "FG_PCT": 0.44480878665243373,
        "FG3_PCT": 0.35815474032464195,
        "FT_PCT": 0.6908416286701821,
        "ptsConfFloor": 22.62374655656805,
        "ptsConfMid": 27.18830409356725,
        "ptsConfTop": 31.752861630566453,
        "astConfFloor": 4.345319414941579,
        "astConfMid": 5.538011695906433,
        "astConfTop": 6.730703976871285,
        "rebConfFloor": 3.9304695976192185,
        "rebConfMid": 4.966081871345029,
        "rebConfTop": 6.001694145070839,
        "team": "SAC",
        "fanduel_pts": 25.5,
        "fanduel_reb": 4.5,
        "fanduel_ast": 5.5,
        "fanduel_threes": 1.5,
        "fanduel_blk": 0,
        "fanduel_stl": 1.5,
        "pick_pts": "OVER",
        "pick_reb": "OVER",
        "pick_ast": "UNDER",
        "pick_3s": "OVER",
        "pick_blk": "OVER",
        "pick_stl": "OVER"
    }
}