{
    "Nick Richards": {
        "MIN": 27.249159978431635,
        "FGM": 4.252450370847565,
        "FGA": 5.901414222322455,
        "FG3M": -0.019845000775651003,
        "FG3A": -0.017411005438635288,
        "REB": 9.264968743522786,
        "AST": 0.753266528347814,
        "STL": 0.40192549619305173,
        "BLK": 1.1488116928365484,
        "PF": 2.728136460353689,
        "PTS": 8.738779439033133,
        "FTA": 2.859801413950939,
        "FTM": 2.2945728675794275,
        "FG_PCT": 0.7936555488784599,
        "FG3_PCT": -0.020427784194248073,
        "FT_PCT": 0.6599950096255398,
        "ptsConfFloor": 7.9250918741875855,
        "ptsConfMid": 10.153968253968253,
        "ptsConfTop": 12.382844633748922,
        "astConfFloor": 0.28538947568703854,
        "astConfMid": 0.6960317460317459,
        "astConfTop": 1.1066740163764535,
        "rebConfFloor": 6.9279147600366,
        "rebConfMid": 8.708333333333334,
        "rebConfTop": 10.488751906630066,
        "team": "CHA",
        "fanduel_pts": 9.5,
        "fanduel_reb": 8.5,
        "fanduel_ast": 0,
        "fanduel_threes": 0,
        "fanduel_blk": 0.5,
        "fanduel_stl": 0,
        "pick_pts": "UNDER",
        "pick_reb": "OVER",
        "pick_ast": "OVER",
        "pick_3s": "UNDER",
        "pick_blk": "OVER",
        "pick_stl": "OVER",
        "pts_res": "W",
        "ast_res": "L",
        "reb_res": "W",
        "stl_res": "L",
        "threes_res": "L",
        "blk_res": "L"
    },
    "Tre Mann": {
        "MIN": 19.38760447485499,
        "FGM": 3.221439949160584,
        "FGA": 6.81667373780229,
        "FG3M": 1.3940699724293584,
        "FG3A": 3.7695441080148564,
        "REB": 4.1293241748227,
        "AST": 4.2925701368267575,
        "STL": 0.9074899350625251,
        "BLK": 0.02868849564227413,
        "PF": 1.1022818934223393,
        "PTS": -1,
        "FTA": 0.6689281765541606,
        "FTM": 0.39453309855940727,
        "FG_PCT": 0.37196831546125086,
        "FG3_PCT": 0.1744491360955287,
        "FT_PCT": 0.3227321416643482,
        "ptsConfFloor": 6.718643037256354,
        "ptsConfMid": 9.271111111111113,
        "ptsConfTop": 11.82357918496587,
        "astConfFloor": 2.2834400838953104,
        "astConfMid": 3.426666666666667,
        "astConfTop": 4.569893249438023,
        "rebConfFloor": 3.306265748156689,
        "rebConfMid": 4.346666666666667,
        "rebConfTop": 5.387067585176644,
        "team": "CHA",
        "fanduel_pts": 10.5,
        "fanduel_reb": 4.5,
        "fanduel_ast": 3.5,
        "fanduel_threes": 1.5,
        "fanduel_blk": 0,
        "fanduel_stl": 0,
        "pick_pts": "UNDER",
        "pick_reb": "UNDER",
        "pick_ast": "OVER",
        "pick_3s": "UNDER",
        "pick_blk": "OVER",
        "pick_stl": "OVER",
        "pts_res": "L",
        "ast_res": "W",
        "reb_res": "W",
        "stl_res": "W",
        "threes_res": "W",
        "blk_res": "L"
    },
    "Simone Fontecchio": {
        "MIN": 22.19830574136244,
        "FGM": 4.4595919673424,
        "FGA": 6.80783007649001,
        "FG3M": 2.029514208856908,
        "FG3A": 4.2551472303176,
        "REB": 4.051837712547677,
        "AST": 1.3706745889702707,
        "STL": 0.7469770498506394,
        "BLK": 0.5776695492723005,
        "PF": 1.6300534694557625,
        "PTS": 9.217962933142111,
        "FTA": 0.8063611257448626,
        "FTM": 0.608752187929114,
        "FG_PCT": 0.4802741075869087,
        "FG3_PCT": 0.4187949168335316,
        "FT_PCT": 0.335841418833843,
        "ptsConfFloor": 9.951690394363576,
        "ptsConfMid": 13.589236111111111,
        "ptsConfTop": 17.22678182785864,
        "astConfFloor": 1.1009449225135957,
        "astConfMid": 1.6934027777777778,
        "astConfTop": 2.2858606330419597,
        "rebConfFloor": 3.4180244968652835,
        "rebConfMid": 4.319444444444445,
        "rebConfTop": 5.220864392023606,
        "team": "DET",
        "fanduel_pts": 14.5,
        "fanduel_reb": 4.5,
        "fanduel_ast": 0,
        "fanduel_threes": 2.5,
        "fanduel_blk": 0,
        "fanduel_stl": 0,
        "pick_pts": "UNDER",
        "pick_reb": "UNDER",
        "pick_ast": "OVER",
        "pick_3s": "UNDER",
        "pick_blk": "OVER",
        "pick_stl": "OVER",
        "pts_res": "L",
        "ast_res": "L",
        "reb_res": "L",
        "stl_res": "W",
        "threes_res": "L",
        "blk_res": "L"
    },
    "Isaiah Stewart": {
        "MIN": 31.69717921633663,
        "FGM": 4.967101135907807,
        "FGA": 8.66852681127121,
        "FG3M": 1.5523525761902295,
        "FG3A": 3.8239371045693504,
        "REB": 6.956374723794891,
        "AST": 1.1740304137248883,
        "STL": 0.34553119129940957,
        "BLK": 0.44617718920151994,
        "PF": 2.7953869220478165,
        "PTS": 10.933278416645264,
        "FTA": 1.8395660908087594,
        "FTM": 1.2127045563527568,
        "FG_PCT": 0.46734383522774897,
        "FG3_PCT": 0.3938670409230568,
        "FT_PCT": 0.6189890676824016,
        "ptsConfFloor": 9.519393286728699,
        "ptsConfMid": 11.35658914728682,
        "ptsConfTop": 13.193785007844946,
        "astConfFloor": 0.6923495632523933,
        "astConfMid": 1.2015503875968994,
        "astConfTop": 1.710751211941405,
        "rebConfFloor": 4.77222406222836,
        "rebConfMid": 6.1214470284237725,
        "rebConfTop": 7.470669994619185,
        "team": "DET",
        "fanduel_pts": 10.5,
        "fanduel_reb": 6.5,
        "fanduel_ast": 0,
        "fanduel_threes": 1.5,
        "fanduel_blk": 0.5,
        "fanduel_stl": 0,
        "pick_pts": "OVER",
        "pick_reb": "OVER",
        "pick_ast": "OVER",
        "pick_3s": "OVER",
        "pick_blk": "UNDER",
        "pick_stl": "OVER",
        "pts_res": "L",
        "ast_res": "W",
        "reb_res": "L",
        "stl_res": "L",
        "threes_res": "W"
    },
    "Jalen Duren": {
        "MIN": 29.204160080778607,
        "FGM": 5.4819404096771045,
        "FGA": 9.870308822987464,
        "FG3M": 0.0,
        "FG3A": 0.09807928513239829,
        "REB": 13.045865535398626,
        "AST": 2.997341995158943,
        "STL": 0.4548729487025475,
        "BLK": 0.9340453458670777,
        "PF": 3.214794057678695,
        "PTS": 15.090064589168284,
        "FTA": 2.95567574065326,
        "FTM": 2.0083875311135406,
        "FG_PCT": 0.6155532724095435,
        "FG3_PCT": 0.0,
        "FT_PCT": 0.45539266611516116,
        "ptsConfFloor": 11.41106441757332,
        "ptsConfMid": 14.39111111111111,
        "ptsConfTop": 17.371157804648902,
        "astConfFloor": 2.1431217174300734,
        "astConfMid": 2.857777777777778,
        "astConfTop": 3.572433838125482,
        "rebConfFloor": 9.842059588054475,
        "rebConfMid": 12.44,
        "rebConfTop": 15.037940411945522,
        "team": "DET",
        "fanduel_pts": 13.5,
        "fanduel_reb": 11.5,
        "fanduel_ast": 0,
        "fanduel_threes": 0,
        "fanduel_blk": 0,
        "fanduel_stl": 0,
        "pick_pts": "OVER",
        "pick_reb": "OVER",
        "pick_ast": "OVER",
        "pick_3s": "UNDER",
        "pick_blk": "OVER",
        "pick_stl": "OVER",
        "pts_res": "W",
        "ast_res": "W",
        "reb_res": "W",
        "stl_res": "L",
        "threes_res": "L",
        "blk_res": "L"
    },
    "Kelly Olynyk": {
        "MIN": 18.891903293785226,
        "FGM": 2.800433338864673,
        "FGA": 3.779587225417075,
        "FG3M": 0.7943451108979753,
        "FG3A": 1.2907597913694484,
        "REB": 5.241480908329048,
        "AST": 4.148407031549786,
        "STL": 1.0625443348059391,
        "BLK": 0.3414214580572718,
        "PF": 2.9129685441556377,
        "PTS": 6.645099471923914,
        "FTA": 1.4964064387188512,
        "FTM": 1.189277560200619,
        "FG_PCT": 0.5859039791186812,
        "FG3_PCT": 0.33807265804652264,
        "FT_PCT": 0.47761032666458614,
        "ptsConfFloor": 9.611932105116216,
        "ptsConfMid": 12.317708333333334,
        "ptsConfTop": 15.023484561550452,
        "astConfFloor": 3.041232360402967,
        "astConfMid": 4.455902777777777,
        "astConfTop": 5.870573195152588,
        "rebConfFloor": 4.4009607190778315,
        "rebConfMid": 5.088888888888889,
        "rebConfTop": 5.7768170586999465,
        "team": "TOR",
        "fanduel_pts": 12.5,
        "fanduel_reb": 6.5,
        "fanduel_ast": 5.5,
        "fanduel_threes": 1.5,
        "fanduel_blk": 0,
        "fanduel_stl": 1.5,
        "pick_pts": "UNDER",
        "pick_reb": "UNDER",
        "pick_ast": "UNDER",
        "pick_3s": "UNDER",
        "pick_blk": "OVER",
        "pick_stl": "UNDER",
        "pts_res": "W",
        "ast_res": "W",
        "reb_res": "L",
        "stl_res": "W",
        "threes_res": "W",
        "blk_res": "L"
    },
    "Immanuel Quickley": {
        "MIN": 25.220746336237298,
        "FGM": 5.712303984677401,
        "FGA": 11.59955932178179,
        "FG3M": 2.145152665423598,
        "FG3A": 5.371532732965305,
        "REB": 4.63366231336865,
        "AST": 6.276391218373439,
        "STL": 0.5415653367952888,
        "BLK": 0.12063604864009243,
        "PF": 1.5279436509445192,
        "PTS": 16.610175037564243,
        "FTA": 2.586809710541725,
        "FTM": 2.234135139813832,
        "FG_PCT": 0.4384668447916579,
        "FG3_PCT": 0.38255342599986125,
        "FT_PCT": 0.7158532108181945,
        "ptsConfFloor": 17.223784988979233,
        "ptsConfMid": 19.683333333333334,
        "ptsConfTop": 22.14288167768743,
        "astConfFloor": 5.12060879558727,
        "astConfMid": 7.1499999999999995,
        "astConfTop": 9.17939120441273,
        "rebConfFloor": 4.033312924119091,
        "rebConfMid": 5.022222222222222,
        "rebConfTop": 6.011131520325354,
        "team": "TOR",
        "fanduel_pts": 22.5,
        "fanduel_reb": 4.5,
        "fanduel_ast": 6.5,
        "fanduel_threes": 2.5,
        "fanduel_blk": 0,
        "fanduel_stl": 1.5,
        "pick_pts": "UNDER",
        "pick_reb": "OVER",
        "pick_ast": "UNDER",
        "pick_3s": "UNDER",
        "pick_blk": "OVER",
        "pick_stl": "UNDER",
        "pts_res": "W",
        "ast_res": "L",
        "reb_res": "L",
        "stl_res": "L",
        "threes_res": "W",
        "blk_res": "L"
    },
    "Bruce Brown": {
        "MIN": 29.831130294038307,
        "FGM": 3.7337352363905847,
        "FGA": 8.40590205233022,
        "FG3M": 1.0429029918036727,
        "FG3A": 2.9257926413388002,
        "REB": 3.569828925121705,
        "AST": 2.0604806420779997,
        "STL": 0.6605740785544638,
        "BLK": 0.22498536298902205,
        "PF": 2.5663883614889804,
        "PTS": 10.798614688033886,
        "FTA": 1.4729606601237886,
        "FTM": 1.7712163485511097,
        "FG_PCT": 0.4810778657322399,
        "FG3_PCT": 0.2938430158511984,
        "FT_PCT": 0.5609283071530573,
        "ptsConfFloor": 6.425761879343752,
        "ptsConfMid": 9.137037037037038,
        "ptsConfTop": 11.848312194730324,
        "astConfFloor": 1.909101353624516,
        "astConfMid": 2.6814814814814816,
        "astConfTop": 3.4538616093384467,
        "rebConfFloor": 2.806047953397973,
        "rebConfMid": 4.35679012345679,
        "rebConfTop": 5.907532293515608,
        "team": "TOR",
        "fanduel_pts": 12.5,
        "fanduel_reb": 5.5,
        "fanduel_ast": 3.5,
        "fanduel_threes": 0,
        "fanduel_blk": 0,
        "fanduel_stl": 0,
        "pick_pts": "UNDER",
        "pick_reb": "UNDER",
        "pick_ast": "UNDER",
        "pick_3s": "OVER",
        "pick_blk": "OVER",
        "pick_stl": "OVER",
        "pts_res": "W",
        "ast_res": "L",
        "reb_res": "W",
        "stl_res": "W",
        "threes_res": "W",
        "blk_res": "L"
    },
    "Brandon Ingram": {
        "MIN": 31.622737952095143,
        "FGM": 8.403970418110271,
        "FGA": 15.963395215035092,
        "FG3M": 1.5313178223098096,
        "FG3A": 4.411791148040386,
        "REB": 5.029491810749355,
        "AST": 5.483455699008705,
        "STL": 0.9457815272832796,
        "BLK": 0.4597333162587441,
        "PF": 2.0504892745496144,
        "PTS": 21.14551147032398,
        "FTA": 4.822632352410082,
        "FTM": 3.9452419187542778,
        "FG_PCT": 0.48931969552221477,
        "FG3_PCT": 0.30214983618892793,
        "FT_PCT": 0.7602816044831823,
        "ptsConfFloor": 15.76570174136792,
        "ptsConfMid": 20.090772128060266,
        "ptsConfTop": 24.415842514752608,
        "astConfFloor": 5.356116062235318,
        "astConfMid": 6.260263653483992,
        "astConfTop": 7.164411244732666,
        "rebConfFloor": 4.5262917130809255,
        "rebConfMid": 5.444821092278719,
        "rebConfTop": 6.363350471476513,
        "team": "NOP",
        "fanduel_pts": 19.5,
        "fanduel_reb": 4.5,
        "fanduel_ast": 5.5,
        "fanduel_threes": 1.5,
        "fanduel_blk": 0,
        "fanduel_stl": 0,
        "pick_pts": "OVER",
        "pick_reb": "OVER",
        "pick_ast": "UNDER",
        "pick_3s": "OVER",
        "pick_blk": "OVER",
        "pick_stl": "OVER",
        "pts_res": "L",
        "ast_res": "L",
        "reb_res": "W",
        "stl_res": "W",
        "threes_res": "W",
        "blk_res": "L"
    },
    "Zion Williamson": {
        "MIN": 30.186069178899462,
        "FGM": 8.589179872689332,
        "FGA": 14.990329070965945,
        "FG3M": -0.00032221616889219207,
        "FG3A": 0.1367269908000865,
        "REB": 5.829721232097974,
        "AST": 5.333846202342818,
        "STL": 0.9435416755748296,
        "BLK": 0.2831905817584333,
        "PF": 2.6270782805575763,
        "PTS": 19.699943305822693,
        "FTA": 5.94579912592411,
        "FTM": 3.7271152279849273,
        "FG_PCT": 0.5434746340465733,
        "FG3_PCT": 0.012480076358595042,
        "FT_PCT": 0.5713603129070207,
        "ptsConfFloor": 18.063506078881446,
        "ptsConfMid": 22.066666666666663,
        "ptsConfTop": 26.069827254451884,
        "astConfFloor": 4.314734062720709,
        "astConfMid": 5.681481481481481,
        "astConfTop": 7.048228900242253,
        "rebConfFloor": 5.029623405602904,
        "rebConfMid": 6.4790123456790125,
        "rebConfTop": 7.928401285755121,
        "team": "NOP",
        "fanduel_pts": 23.5,
        "fanduel_reb": 6.5,
        "fanduel_ast": 5.5,
        "fanduel_threes": 0,
        "fanduel_blk": 0,
        "fanduel_stl": 0,
        "pick_pts": "UNDER",
        "pick_reb": "UNDER",
        "pick_ast": "UNDER",
        "pick_3s": "UNDER",
        "pick_blk": "OVER",
        "pick_stl": "OVER",
        "pts_res": "L",
        "ast_res": "W",
        "reb_res": "L",
        "stl_res": "W",
        "threes_res": "L",
        "blk_res": "L"
    },
    "Jonas Valanciunas": {
        "MIN": 25.624494443081378,
        "FGM": 4.4361320744501995,
        "FGA": 9.38979935033202,
        "FG3M": 0.8148857724968533,
        "FG3A": 2.0391691111405152,
        "REB": 9.00986079954543,
        "AST": 1.8471535148554408,
        "STL": 0.5568493773967872,
        "BLK": 1.153094308237149,
        "PF": 2.464357072197388,
        "PTS": 12.169817285976018,
        "FTA": 3.014261065098212,
        "FTM": 2.357280546223638,
        "FG_PCT": 0.552744280059095,
        "FG3_PCT": 0.22174810974341316,
        "FT_PCT": 0.7000734460126824,
        "ptsConfFloor": 7.942824239638615,
        "ptsConfMid": 10.193162393162392,
        "ptsConfTop": 12.443500546686172,
        "astConfFloor": 1.367920279713373,
        "astConfMid": 1.8393162393162392,
        "astConfTop": 2.3107121989191057,
        "rebConfFloor": 8.010643988800764,
        "rebConfMid": 9.04273504273504,
        "rebConfTop": 10.074826096669323,
        "team": "NOP",
        "fanduel_pts": 9.5,
        "fanduel_reb": 7.5,
        "fanduel_ast": 0,
        "fanduel_threes": 0,
        "fanduel_blk": 0,
        "fanduel_stl": 0,
        "pick_pts": "OVER",
        "pick_reb": "OVER",
        "pick_ast": "OVER",
        "pick_3s": "OVER",
        "pick_blk": "OVER",
        "pick_stl": "OVER",
        "pts_res": "L",
        "ast_res": "L",
        "reb_res": "L",
        "stl_res": "L",
        "threes_res": "L",
        "blk_res": "L"
    },
    "Herbert Jones": {
        "MIN": 29.073841580672337,
        "FGM": 4.317483444953208,
        "FGA": 7.5531502894260765,
        "FG3M": 1.5671573898242068,
        "FG3A": 3.925962425257083,
        "REB": 3.8529028956601508,
        "AST": 2.321463351879328,
        "STL": 1.2102166056489305,
        "BLK": 0.7467332590000727,
        "PF": 3.3009238015521465,
        "PTS": 10.180390477374939,
        "FTA": 2.2846928986714974,
        "FTM": 1.8977239863887845,
        "FG_PCT": 0.4896487856226037,
        "FG3_PCT": 0.29724561438642005,
        "FT_PCT": 0.6156159765595465,
        "ptsConfFloor": 7.67436362435367,
        "ptsConfMid": 10.172222222222222,
        "ptsConfTop": 12.670080820090774,
        "astConfFloor": 1.8976645975381248,
        "astConfMid": 2.4444444444444446,
        "astConfTop": 2.9912242913507643,
        "rebConfFloor": 2.325168403349464,
        "rebConfMid": 3.238888888888889,
        "rebConfTop": 4.152609374428313,
        "team": "NOP",
        "fanduel_pts": 9.5,
        "fanduel_reb": 3.5,
        "fanduel_ast": 0,
        "fanduel_threes": 1.5,
        "fanduel_blk": 0,
        "fanduel_stl": 1.5,
        "pick_pts": "OVER",
        "pick_reb": "OVER",
        "pick_ast": "OVER",
        "pick_3s": "OVER",
        "pick_blk": "OVER",
        "pick_stl": "UNDER",
        "pts_res": "L",
        "ast_res": "W",
        "reb_res": "W",
        "stl_res": "W",
        "threes_res": "W"
    },
    "CJ McCollum": {
        "MIN": 31.263163970573654,
        "FGM": 7.075280173566515,
        "FGA": 14.837764841170248,
        "FG3M": 3.1987433276939927,
        "FG3A": 8.043219154923591,
        "REB": 4.581005507582072,
        "AST": 3.24506436200447,
        "STL": 1.239495355691995,
        "BLK": 0.6930996148385734,
        "PF": 2.037517071312513,
        "PTS": 16.278644143951595,
        "FTA": 2.205475008060395,
        "FTM": 1.9141078912028684,
        "FG_PCT": 0.4281662309078276,
        "FG3_PCT": 0.42753350017569164,
        "FT_PCT": 0.6104078016050959,
        "ptsConfFloor": 13.01276532716733,
        "ptsConfMid": 15.761904761904761,
        "ptsConfTop": 18.511044196642192,
        "astConfFloor": 2.412868126997298,
        "astConfMid": 3.184126984126984,
        "astConfTop": 3.95538584125667,
        "rebConfFloor": 3.7057608934814343,
        "rebConfMid": 4.1328798185941045,
        "rebConfTop": 4.559998743706774,
        "team": "NOP",
        "fanduel_pts": 16.5,
        "fanduel_reb": 3.5,
        "fanduel_ast": 3.5,
        "fanduel_threes": 2.5,
        "fanduel_blk": 0,
        "fanduel_stl": 0,
        "pick_pts": "UNDER",
        "pick_reb": "OVER",
        "pick_ast": "UNDER",
        "pick_3s": "OVER",
        "pick_blk": "OVER",
        "pick_stl": "OVER",
        "pts_res": "W",
        "ast_res": "L",
        "reb_res": "W",
        "stl_res": "W",
        "threes_res": "L",
        "blk_res": "L"
    },
    "Julian Champagnie": {
        "MIN": 15.935092661271726,
        "FGM": 1.8592836491605729,
        "FGA": 3.9878826909670155,
        "FG3M": 1.1429201114382426,
        "FG3A": 2.4987753584117707,
        "REB": 2.955580548940081,
        "AST": 1.3761530795354355,
        "STL": 0.7382428850134173,
        "BLK": 0.7300747389840825,
        "PF": 0.8098496269102806,
        "PTS": 4.995707143905277,
        "FTA": 0.5685446649963296,
        "FTM": 0.3552725663573542,
        "FG_PCT": 0.30900627148168225,
        "FG3_PCT": 0.28521315255438406,
        "FT_PCT": 0.2512883710726136,
        "ptsConfFloor": 4.200106972253554,
        "ptsConfMid": 6.783524904214559,
        "ptsConfTop": 9.366942836175564,
        "astConfFloor": 0.8625118458064951,
        "astConfMid": 1.6697318007662834,
        "astConfTop": 2.476951755726072,
        "rebConfFloor": 2.021620023504335,
        "rebConfMid": 3.006896551724138,
        "rebConfTop": 3.9921730799439406,
        "team": "SAS",
        "fanduel_pts": 0,
        "fanduel_reb": 0,
        "fanduel_ast": 0,
        "fanduel_threes": 0,
        "fanduel_blk": 0,
        "fanduel_stl": 0,
        "pick_pts": "OVER",
        "pick_reb": "OVER",
        "pick_ast": "OVER",
        "pick_3s": "OVER",
        "pick_blk": "OVER",
        "pick_stl": "OVER",
        "pts_res": "W",
        "ast_res": "W",
        "reb_res": "W",
        "stl_res": "L",
        "threes_res": "W",
        "blk_res": "L"
    },
    "Jeremy Sochan": {
        "MIN": 29.588213183772766,
        "FGM": 4.363258953372652,
        "FGA": 8.874143206586915,
        "FG3M": 1.0247690334849895,
        "FG3A": 2.511426784070473,
        "REB": 6.1599798466739415,
        "AST": 2.590418054441354,
        "STL": 0.7750103576095735,
        "BLK": 0.4350043611567838,
        "PF": 2.379099807696744,
        "PTS": 10.865484184722696,
        "FTA": 1.6375716977541737,
        "FTM": 1.2091144591534624,
        "FG_PCT": 0.3825241710215329,
        "FG3_PCT": 0.3144183992084306,
        "FT_PCT": 0.4508347839572102,
        "ptsConfFloor": 10.050867074036587,
        "ptsConfMid": 12.841414141414141,
        "ptsConfTop": 15.631961208791699,
        "astConfFloor": 1.9242573203783089,
        "astConfMid": 2.914141414141414,
        "astConfTop": 3.9040255079045196,
        "rebConfFloor": 5.663793206248717,
        "rebConfMid": 6.609090909090909,
        "rebConfTop": 7.5543886119331,
        "team": "SAS",
        "fanduel_pts": 10.5,
        "fanduel_reb": 6.5,
        "fanduel_ast": 0,
        "fanduel_threes": 0.5,
        "fanduel_blk": 0,
        "fanduel_stl": 0,
        "pick_pts": "OVER",
        "pick_reb": "UNDER",
        "pick_ast": "OVER",
        "pick_3s": "OVER",
        "pick_blk": "OVER",
        "pick_stl": "OVER",
        "pts_res": "W",
        "ast_res": "W",
        "reb_res": "W",
        "stl_res": "W",
        "threes_res": "W",
        "blk_res": "L"
    },
    "Devin Vassell": {
        "MIN": 31.103411499999535,
        "FGM": 8.108700924738972,
        "FGA": 14.226597085544457,
        "FG3M": 2.5160129299068927,
        "FG3A": 7.1023952463354805,
        "REB": 4.4829376619853925,
        "AST": 4.593036658256072,
        "STL": 1.0514712614381219,
        "BLK": 0.22404375020555672,
        "PF": 0.8651734083648189,
        "PTS": 17.675783726304367,
        "FTA": 3.5724662814304677,
        "FTM": 2.6811116042739354,
        "FG_PCT": 0.46039020746092957,
        "FG3_PCT": 0.3827559121535064,
        "FT_PCT": 0.725255944588574,
        "ptsConfFloor": 15.66021732361343,
        "ptsConfMid": 19.472222222222225,
        "ptsConfTop": 23.28422712083101,
        "astConfFloor": 3.4038594616842315,
        "astConfMid": 4.627777777777777,
        "astConfTop": 5.8516960938713245,
        "rebConfFloor": 3.458951220173207,
        "rebConfMid": 4.7444444444444445,
        "rebConfTop": 6.029937668715682,
        "team": "SAS",
        "fanduel_pts": 18.5,
        "fanduel_reb": 3.5,
        "fanduel_ast": 4.5,
        "fanduel_threes": 2.5,
        "fanduel_blk": 0,
        "fanduel_stl": 0,
        "pick_pts": "UNDER",
        "pick_reb": "OVER",
        "pick_ast": "OVER",
        "pick_3s": "OVER",
        "pick_blk": "OVER",
        "pick_stl": "OVER",
        "pts_res": "W",
        "ast_res": "L",
        "reb_res": "L",
        "stl_res": "W",
        "threes_res": "W"
    },
    "Tre Jones": {
        "MIN": 25.575106903949475,
        "FGM": 3.109661775302205,
        "FGA": 6.750290014622399,
        "FG3M": 0.5908619917617949,
        "FG3A": 2.341794714949841,
        "REB": 3.5455641948382213,
        "AST": 6.771756109091802,
        "STL": 0.9304334994753412,
        "BLK": 0.13229351184021917,
        "PF": 1.204827012019291,
        "PTS": 8.102630148782909,
        "FTA": 1.317307082056371,
        "FTM": 1.1438583238006512,
        "FG_PCT": 0.46543176189712804,
        "FG3_PCT": 0.2498316426688132,
        "FT_PCT": 0.45088539157867225,
        "ptsConfFloor": 5.549810155830638,
        "ptsConfMid": 9.029872495446266,
        "ptsConfTop": 12.509934835061893,
        "astConfFloor": 5.441909910852342,
        "astConfMid": 6.899817850637523,
        "astConfTop": 8.357725790422705,
        "rebConfFloor": 3.2524884300265557,
        "rebConfMid": 3.897996357012751,
        "rebConfTop": 4.543504283998946,
        "team": "SAS",
        "fanduel_pts": 8.5,
        "fanduel_reb": 2.5,
        "fanduel_ast": 6.5,
        "fanduel_threes": 0,
        "fanduel_blk": 0,
        "fanduel_stl": 0,
        "pick_pts": "UNDER",
        "pick_reb": "OVER",
        "pick_ast": "OVER",
        "pick_3s": "OVER",
        "pick_blk": "OVER",
        "pick_stl": "OVER",
        "pts_res": "W",
        "ast_res": "W",
        "reb_res": "W",
        "stl_res": "W",
        "threes_res": "W",
        "blk_res": "L"
    },
    "John Collins": {
        "MIN": 28.44364879609085,
        "FGM": 6.242963971425956,
        "FGA": 10.91159887160803,
        "FG3M": 0.9982150534014829,
        "FG3A": 3.290515624057112,
        "REB": 9.783150893783287,
        "AST": 1.4266698760501821,
        "STL": 0.5445384361200396,
        "BLK": 1.0333805827671574,
        "PF": 2.9484648475568993,
        "PTS": 14.716101720374379,
        "FTA": 2.4319734064803376,
        "FTM": 2.2470527744659075,
        "FG_PCT": 0.5204216838814896,
        "FG3_PCT": 0.31998160932870084,
        "FT_PCT": 0.6173793337061495,
        "ptsConfFloor": 13.683347837059015,
        "ptsConfMid": 16.11912568306011,
        "ptsConfTop": 18.554903529061207,
        "astConfFloor": 0.6678103184338404,
        "astConfMid": 1.232422586520947,
        "astConfTop": 1.797034854608054,
        "rebConfFloor": 7.283550684687515,
        "rebConfMid": 9.258287795992715,
        "rebConfTop": 11.233024907297915,
        "team": "UTA",
        "fanduel_pts": 16.5,
        "fanduel_reb": 9.5,
        "fanduel_ast": 0,
        "fanduel_threes": 1.5,
        "fanduel_blk": 1.5,
        "fanduel_stl": 0.5,
        "pick_pts": "UNDER",
        "pick_reb": "OVER",
        "pick_ast": "OVER",
        "pick_3s": "UNDER",
        "pick_blk": "UNDER",
        "pick_stl": "OVER",
        "pts_res": "L",
        "ast_res": "W",
        "reb_res": "W",
        "stl_res": "L",
        "threes_res": "L",
        "blk_res": "W"
    },
    "Collin Sexton": {
        "MIN": 23.31503841453517,
        "FGM": 5.977601027287941,
        "FGA": 13.002559308046674,
        "FG3M": 1.6258303345385432,
        "FG3A": 4.070486573421042,
        "REB": 2.432399541572197,
        "AST": 5.367072576337755,
        "STL": 0.662750344771927,
        "BLK": 0.15638936871549258,
        "PF": 1.9541288540910595,
        "PTS": 17.717443067790676,
        "FTA": 4.41633958349497,
        "FTM": 3.9582144854267733,
        "FG_PCT": 0.4211228583527017,
        "FG3_PCT": 0.3409104496635097,
        "FT_PCT": 0.7755648894399668,
        "ptsConfFloor": 17.6953321713089,
        "ptsConfMid": 20.133333333333336,
        "ptsConfTop": 22.57133449535777,
        "astConfFloor": 4.4516068003977445,
        "astConfMid": 5.252991452991453,
        "astConfTop": 6.054376105585162,
        "rebConfFloor": 1.7547436203046913,
        "rebConfMid": 2.772649572649573,
        "rebConfTop": 3.790555524994454,
        "team": "UTA",
        "fanduel_pts": 22.5,
        "fanduel_reb": 3.5,
        "fanduel_ast": 6.5,
        "fanduel_threes": 2.5,
        "fanduel_blk": 0,
        "fanduel_stl": 0.5,
        "pick_pts": "UNDER",
        "pick_reb": "UNDER",
        "pick_ast": "UNDER",
        "pick_3s": "UNDER",
        "pick_blk": "OVER",
        "pick_stl": "OVER",
        "pts_res": "W",
        "ast_res": "W",
        "reb_res": "L",
        "stl_res": "W",
        "threes_res": "L",
        "blk_res": "L"
    },
    "Clint Capela": {
        "MIN": 26.067591558940634,
        "FGM": 4.666282828526041,
        "FGA": 8.952805900758118,
        "FG3M": 0.0,
        "FG3A": 0.0,
        "REB": 11.268235622042823,
        "AST": 1.3212838069402475,
        "STL": 0.6172958268664533,
        "BLK": 1.789810788492705,
        "PF": 2.5304168578880493,
        "PTS": 13.204184962910697,
        "FTA": 2.893859674724033,
        "FTM": 1.9886501062971653,
        "FG_PCT": 0.5416503401267717,
        "FG3_PCT": 0.0,
        "FT_PCT": 0.5958387836899371,
        "ptsConfFloor": 10.227726331112017,
        "ptsConfMid": 12.06549707602339,
        "ptsConfTop": 13.903267820934767,
        "astConfFloor": 0.8409977874113581,
        "astConfMid": 1.439766081871345,
        "astConfTop": 2.0385343763313317,
        "rebConfFloor": 9.549848906771947,
        "rebConfMid": 10.818713450292398,
        "rebConfTop": 12.087577993812848,
        "team": "ATL",
        "fanduel_pts": 12.5,
        "fanduel_reb": 10.5,
        "fanduel_ast": 0,
        "fanduel_threes": 0,
        "fanduel_blk": 1.5,
        "fanduel_stl": 0.5,
        "pick_pts": "OVER",
        "pick_reb": "OVER",
        "pick_ast": "OVER",
        "pick_3s": "UNDER",
        "pick_blk": "OVER",
        "pick_stl": "OVER",
        "pts_res": "L",
        "ast_res": "W",
        "stl_res": "L",
        "threes_res": "L",
        "blk_res": "L"
    },
    "Dejounte Murray": {
        "MIN": 34.788873310406764,
        "FGM": 7.96895380416797,
        "FGA": 18.4663534007085,
        "FG3M": 2.8153420413929875,
        "FG3A": 6.736100388411205,
        "REB": 5.351931629630552,
        "AST": 6.053544202689828,
        "STL": 1.384917784178972,
        "BLK": 0.3671809645920145,
        "PF": 1.7868881265023346,
        "PTS": 22.65193366988946,
        "FTA": 3.000385275523433,
        "FTM": 2.8317625837310874,
        "FG_PCT": 0.45445545591571646,
        "FG3_PCT": 0.3784721657450758,
        "FT_PCT": 0.6594337340362473,
        "ptsConfFloor": 20.465322515764864,
        "ptsConfMid": 24.93189964157706,
        "ptsConfTop": 29.39847676738926,
        "astConfFloor": 5.451319761243783,
        "astConfMid": 6.786021505376344,
        "astConfTop": 8.120723249508904,
        "rebConfFloor": 3.814444898245124,
        "rebConfMid": 5.186379928315412,
        "rebConfTop": 6.558314958385701,
        "team": "ATL",
        "fanduel_pts": 26.5,
        "fanduel_reb": 5.5,
        "fanduel_ast": 8.5,
        "fanduel_threes": 3.5,
        "fanduel_blk": 0,
        "fanduel_stl": 1.5,
        "pick_pts": "UNDER",
        "pick_reb": "UNDER",
        "pick_ast": "UNDER",
        "pick_3s": "UNDER",
        "pick_blk": "OVER",
        "pick_stl": "UNDER",
        "pts_res": "L",
        "ast_res": "L",
        "reb_res": "L",
        "stl_res": "L",
        "threes_res": "L",
        "blk_res": "L"
    },
    "overall": 0.5333333333333333,
    "pts": 0.5238095238095238,
    "ast": 0.5714285714285714,
    "reb": 0.5714285714285714,
    "threes": 0.42857142857142855,
    "stl": 0.5714285714285714,
    "bestBetsPts": 0.0,
    "bestBetsAst": 0.3333333333333333,
    "bestBetsReb": 1.0
}