{
    "1631106": "HOU",
    "1630578": "HOU",
    "1630256": "HOU",
    "1630535": "DAL",
    "1630182": "DAL",
    "1641726": "DAL",
    "1629660": "CLE",
    "1629731": "CLE",
    "202695": "LAC",
    "1630563": "LAC",
    "1626196": "MIA",
    "1631097": "IND",
    "1641739": "POR",
    "1629057": "POR",
    "1627763": "POR",
    "1631101": "POR",
    "1629014": "POR",
    "1629680": "POR",
    "203897": "CHI",
    "1630172": "CHI",
    "1641763": "CHI",
    "1627742": "NOP",
    "1641731": "WAS",
    "1628963": "WAS",
    "1626145": "WAS",
    "1629013": "WAS",
    "1630567": "TOR",
    "1628449": "TOR",
    "1627751": "TOR",
    "1629007": "TOR",
    "1628983": "OKC",
    "1630163": "CHA",
    "203552": "CHA",
    "1628998": "CHA",
    "1631109": "CHA",
    "203944": "NYK",
    "1630699": "MIL",
    "1629001": "PHI",
    "1629646": "SAS",
    "1631110": "SAS",
    "1630170": "SAS",
    "1631230": "SAS",
    "1626224": "SAS",
    "1628989": "SAC",
    "1628370": "SAC",
    "1628966": "BKN",
    "1627732": "BKN",
    "1641727": "BKN",
    "203903": "UTA",
    "1628381": "UTA",
    "1631117": "UTA",
    "1628374": "UTA",
    "201939": "GSW",
    "203967": "GSW",
    "1626157": "MIN",
    "1641720": "LAL",
    "1629020": "LAL",
    "1626174": "LAL"
}